Workbook

Sheet Info Page
B2: Legend | E2: Yep thats all, the rest was just me cookin
B3: User Inputs | C3: 0

Sheet Goals & Options
B1: Saving Goals | E1: Mortgage / Debt Options | L1: Mortgage / Debt Options (Not working)
B2: Emergency Fund | E2: Option 1 - Pay it off | L2: Option 1 - Pay it off | N2: Option 2 - Save it all | P2: Option 3 - Half/Half
B3: =(Budgeting!L33*C4) | J3: Repayments | L3: Saved | N3: Saved | P3: Saved
B4: Months | C4: 6 | J4: 1000 | L4: =('Housing Costs'!$D$15*12*PMT('Housing Costs'!$D$17/12, 'Housing Costs'!$D$15*12, -'Housing Costs'!$B$9) - 'Housing Costs'!$B$9) - ((PMT('Housing Costs'!$D$17/12, 'Housing Costs'!$D$15*12, -('Housing Costs'!$B$9 - (M7*12*'Housing Costs'!$D$15/2))) + L7) * NPER('Housing Costs'!$D$17/12, -(PMT('Housing Costs'!$D$17/12, 'Housing Costs'!$D$15*12, -('Housing Costs'!$B$9 - (M7*12*'Housing Costs'!$D$15/2))) + L7), 'Housing Costs'!$B$9 - (M7*12*'Housing Costs'!$D$15/2)) - 'Housing Costs'!$B$9) | N4: =('Housing Costs'!$D$15*12*PMT('Housing Costs'!$D$17/12, 'Housing Costs'!$D$15*12, -'Housing Costs'!$B$9) - 'Housing Costs'!$B$9) - ((PMT('Housing Costs'!$D$17/12, 'Housing Costs'!$D$15*12, -('Housing Costs'!$B$9 - (O7*12*'Housing Costs'!$D$15/2))) + N7) * NPER('Housing Costs'!$D$17/12, -(PMT('Housing Costs'!$D$17/12, 'Housing Costs'!$D$15*12, -('Housing Costs'!$B$9 - (O7*12*'Housing Costs'!$D$15/2))) + N7), 'Housing Costs'!$B$9 - (O7*12*'Housing Costs'!$D$15/2)) - 'Housing Costs'!$B$9) | P4: =('Housing Costs'!$D$15*12*PMT('Housing Costs'!$D$17/12, 'Housing Costs'!$D$15*12, -'Housing Costs'!$B$9) - 'Housing Costs'!$B$9) - ((PMT('Housing Costs'!$D$17/12, 'Housing Costs'!$D$15*12, -('Housing Costs'!$B$9 - (Q7*12*'Housing Costs'!$D$15/2))) + P7) * NPER('Housing Costs'!$D$17/12, -(PMT('Housing Costs'!$D$17/12, 'Housing Costs'!$D$15*12, -('Housing Costs'!$B$9 - (Q7*12*'Housing Costs'!$D$15/2))) + P7), 'Housing Costs'!$B$9 - (Q7*12*'Housing Costs'!$D$15/2)) - 'Housing Costs'!$B$9)
B5: Months to gather | J5: Savings | L5: =IF( ('Housing Costs'!$D$15 - NPER( 'Housing Costs'!$D$17/12, -(PMT('Housing Costs'!$D$17/12, 'Housing Costs'!$D$15*12, -('Housing Costs'!$B$9 - (M7*12*'Housing Costs'!$D$15/2))) + L7), 'Housing Costs'!$B$9 - (M7*12*'Housing Costs'!$D$15/2) ) / 12 ) > 0, INT('Housing Costs'!$D$15 - NPER( 'Housing Costs'!$D$17/12, -(PMT('Housing Costs'!$D$17/12, 'Housing Costs'!$D$15*12, -('Housing Costs'!$B$9 - (M7*12*'Housing Costs'!$D$15/2))) + L7), 'Housing Costs'!$B$9 - (M7*12*'Housing Costs'!$D$15/2) ) / 12 ) & " Years, " & INT(MOD( 'Housing Costs'!$D$15 - NPER( 'Housing Costs'!$D$17/12, -(PMT('Housing Costs'!$D$17/12, 'Housing Costs'!$D$15*12, -('Housing Costs'!$B$9 - (M7*12*'Housing Costs'!$D$15/2))) + L7), 'Housing Costs'!$B$9 - (M7*12*'Housing Costs'!$D$15/2) ) / 12, 1 ) * 12) & " Months", "Not Saving Time" ) | N5: =IF( ('Housing Costs'!$D$15 - NPER( 'Housing Costs'!$D$17/12, -(PMT('Housing Costs'!$D$17/12, 'Housing Costs'!$D$15*12, -('Housing Costs'!$B$9 - (O7*12*'Housing Costs'!$D$15/2))) + N7), 'Housing Costs'!$B$9 - (O7*12*'Housing Costs'!$D$15/2) ) / 12 ) > 0, INT('Housing Costs'!$D$15 - NPER( 'Housing Costs'!$D$17/12, -(PMT('Housing Costs'!$D$17/12, 'Housing Costs'!$D$15*12, -('Housing Costs'!$B$9 - (O7*12*'Housing Costs'!$D$15/2))) + N7), 'Housing Costs'!$B$9 - (O7*12*'Housing Costs'!$D$15/2) ) / 12 ) & " Years, " & INT(MOD( 'Housing Costs'!$D$15 - NPER( 'Housing Costs'!$D$17/12, -(PMT('Housing Costs'!$D$17/12, 'Housing Costs'!$D$15*12, -('Housing Costs'!$B$9 - (O7*12*'Housing Costs'!$D$15/2))) + N7), 'Housing Costs'!$B$9 - (O7*12*'Housing Costs'!$D$15/2) ) / 12, 1 ) * 12) & " Months", "Not Saving Time" ) | P5: =IF( ('Housing Costs'!$D$15 - NPER( 'Housing Costs'!$D$17/12, -(PMT('Housing Costs'!$D$17/12, 'Housing Costs'!$D$15*12, -('Housing Costs'!$B$9 - (Q7*12*'Housing Costs'!$D$15/2))) + P7), 'Housing Costs'!$B$9 - (Q7*12*'Housing Costs'!$D$15/2) ) / 12 ) > 0, INT('Housing Costs'!$D$15 - NPER( 'Housing Costs'!$D$17/12, -(PMT('Housing Costs'!$D$17/12, 'Housing Costs'!$D$15*12, -('Housing Costs'!$B$9 - (Q7*12*'Housing Costs'!$D$15/2))) + P7), 'Housing Costs'!$B$9 - (Q7*12*'Housing Costs'!$D$15/2) ) / 12 ) & " Years, " & INT(MOD( 'Housing Costs'!$D$15 - NPER( 'Housing Costs'!$D$17/12, -(PMT('Housing Costs'!$D$17/12, 'Housing Costs'!$D$15*12, -('Housing Costs'!$B$9 - (Q7*12*'Housing Costs'!$D$15/2))) + P7), 'Housing Costs'!$B$9 - (Q7*12*'Housing Costs'!$D$15/2) ) / 12, 1 ) * 12) & " Months", "Not Saving Time" )
B6: =IFERROR(INT(B3/IF(B8,IF(C8,Budgeting!L23+Budgeting!L25,Budgeting!L23),IF(C8,Budgeting!L23,0))/12) & " Years, " & INT(MOD(B3/IF(B8,IF(C8,Budgeting!L23+Budgeting!L25,Budgeting!L23),IF(C8,Budgeting!L23,0)),12)) & " Months","Not Saving") | J6: 0 | L6: Repayments | M6: Savings | N6: Repayments | O6: Savings | P6: Repayments | Q6: Savings
B7: Invest | C7: Savings | L7: 1000 | M7: 0 | N7: 0 | O7: 1000 | P7: 500 | Q7: 500
B8: TRUE | C8: TRUE | L8: Total Interest | N8: Total Interest | P8: Total Interest
L9: =('Housing Costs'!$D$15 * 12 * PMT('Housing Costs'!$D$17 / 12, 'Housing Costs'!$D$15 * 12, -'Housing Costs'!$B$9)) - 'Housing Costs'!$B$9 | N9: =('Housing Costs'!$D$15 * 12 * PMT('Housing Costs'!$D$17 / 12, 'Housing Costs'!$D$15 * 12, -'Housing Costs'!$B$9)) - 'Housing Costs'!$B$9 | P9: =('Housing Costs'!$D$15 * 12 * PMT('Housing Costs'!$D$17 / 12, 'Housing Costs'!$D$15 * 12, -'Housing Costs'!$B$9)) - 'Housing Costs'!$B$9
E10: Option 2 - Save it all | L10: New Interest | N10: New Interest | P10: New Interest
J11: Repayments | L11: =((PMT('Housing Costs'!$D$17 / 12, 'Housing Costs'!$D$15 * 12, -('Housing Costs'!$B$9 - (M7 * 12 * 'Housing Costs'!$D$15 / 2))) + L7) * NPER( 'Housing Costs'!$D$17 / 12, -(PMT('Housing Costs'!$D$17 / 12, 'Housing Costs'!$D$15 * 12, -('Housing Costs'!$B$9 - (M7 * 12 * 'Housing Costs'!$D$15 / 2))) + L7), 'Housing Costs'!$B$9 - (M7 * 12 * 'Housing Costs'!$D$15 / 2) )) - ('Housing Costs'!$B$9 - (M7 * 12 * 'Housing Costs'!$D$15 / 2)) | N11: =((PMT('Housing Costs'!$D$17 / 12, 'Housing Costs'!$D$15 * 12, -('Housing Costs'!$B$9 - (O7 * 12 * 'Housing Costs'!$D$15 / 2))) + N7) * NPER( 'Housing Costs'!$D$17 / 12, -(PMT('Housing Costs'!$D$17 / 12, 'Housing Costs'!$D$15 * 12, -('Housing Costs'!$B$9 - (O7 * 12 * 'Housing Costs'!$D$15 / 2))) + N7), 'Housing Costs'!$B$9 - (O7 * 12 * 'Housing Costs'!$D$15 / 2) )) - ('Housing Costs'!$B$9 - (O7 * 12 * 'Housing Costs'!$D$15 / 2)) | P11: =((PMT('Housing Costs'!$D$17 / 12, 'Housing Costs'!$D$15 * 12, -('Housing Costs'!$B$9 - (Q7 * 12 * 'Housing Costs'!$D$15 / 2))) + P7) * NPER( 'Housing Costs'!$D$17 / 12, -(PMT('Housing Costs'!$D$17 / 12, 'Housing Costs'!$D$15 * 12, -('Housing Costs'!$B$9 - (Q7 * 12 * 'Housing Costs'!$D$15 / 2))) + P7), 'Housing Costs'!$B$9 - (Q7 * 12 * 'Housing Costs'!$D$15 / 2) )) - ('Housing Costs'!$B$9 - (Q7 * 12 * 'Housing Costs'!$D$15 / 2))
J12: 0 | L12: Saved | N12: Saved | P12: Saved
J13: Savings | L13: =(L9-L11) | N13: =(N9-N11) | P13: =(P9-P11)
J14: 1000
E18: Option 3 - Half/Half
J19: Repayments
J20: 500
J21: Savings
J22: 500

Sheet Budgeting
B2: Current Budget
B3: Family | D3: P1 | F3: P2 | H3: Joint Income | K3: Family | M3: P1 | O3: P2 | Q3: Joint Income
B4: Rent / Mortgage | C4: 2400 | D4: Phone | E4: 50 | H4: =IF(I13,SUM(Income!H23,Income!H5)+(I25*12),SUM(Income!H23,Income!H5)) | Q4: =IF(I13,SUM(Income!H23,Income!H5)+(I25*12),SUM(Income!H23,Income!H5))
B5: Electricity | C5: 115 | D5: Car rego | E5: 75 | H5: Ratio | Q5: Ratio
B6: Internet | C6: 85 | H6: P1 | I6: P2 | Q6: P1 | R6: P2
B7: Groceries | C7: 1083.3333 | H7: =IF(I13,Income!H5/(H4-(I25*12)),Income!H5/H4) | I7: =IF(I13,Income!H23/(H4-(I25*12)),Income!H23/H4) | Q7: =IF(I13,Income!H5/(H4-(I25*12)),Income!H5/H4) | R7: =IF(I13,Income!H23/(H4-(I25*12)),Income!H23/H4)
H8: Expense Settings | Q8: Expense Settings
H9: All Joint | I9: Income Ratio | Q9: All Joint | R9: Income Ratio
H10: FALSE | I10: TRUE | Q10: FALSE | R10: TRUE
H11: Roomie | Q11: Roomie
H12: No Roomate | I12: Add to income | Q12: No Roomate | R12: Add to income
H13: TRUE | I13: FALSE | Q13: TRUE | R13: FALSE
B15: Total Month | C15: =IF(I13,SUM(C4:C14),(SUM(C4:C14)-I25)) | D15: Total Month | E15: =SUM(E4:E14) | F15: Total Month | G15: =SUM(G4:G14) | K15: Total Month | L15: =IF(R13,SUM(L4:L14),(SUM(L4:L14)-R25)) | M15: Total Month | N15: =SUM(N4:N14) | O15: Total Month | P15: =SUM(P4:P14)
B16: Total Expense | C16: =SUM(C15,E15,G15) | D16: P1 | E16: =IF(I10,IF(H10,C16*H7,(C15*H7)+E15),IF(H10,C16*0.5,(C15*0.5)+E15)) | F16: P2 (Fortnightly) | G16: =IF(I10,IF(H10,C16*I7,(C15*I7)+G15),IF(H10,C16*0.5,(C15*0.5)+G15))*12/26 | K16: Total Expense | L16: =SUM(L15,N15,P15) | M16: P1 | N16: =IF(R10,IF(Q10,L16*Q7,(L15*Q7)+N15),IF(Q10,L16*0.5,(L15*0.5)+N15)) | O16: P2 (Fortnightly) | P16: =IF(R10,IF(Q10,L16*R7,(L15*R7)+P15),IF(Q10,L16*0.5,(L15*0.5)+P15))*12/26
B17: Total Income | C17: =H4/12 | D17: Monthly Income | E17: =(H4*H7)/12 | F17: Fortnightly Income | G17: =(H4*I7)/26 | K17: Total Income | L17: =Q4/12 | M17: Monthly Income | N17: =(Q4*Q7)/12 | O17: Fortnightly Income | P17: =(Q4*R7)/26
B18: Joint After Bills | D18: Remainder | E18: =E17-E16 | F18: Remainder | G18: =G17-G16 | K18: Joint After Bills | M18: Remainder | N18: =N17-N16 | O18: Remainder | P18: =P17-P16
B19: Total | C19: 600 | D19: General | E19: =IF(I10,C19*H7,C19*0.5) | F19: General | G19: =IF(I10,C19*I7,C19*0.5)*12/26 | K19: Total | N19: =IF(R10,L19*Q7,L19*0.5) | P19: =IF(R10,L19*R7,L19*0.5)*12/26
D20: Remainder | E20: =E18-E19 | F20: Remainder | G20: =G18-G19 | M20: Remainder | N20: =N18-N19 | O20: Remainder | P20: =P18-P19
B21: Total | C21: 600 | D21: Shared Account | E21: =IF(I10,C21*H7,C21*0.5) | F21: Shared Account | G21: =IF(I10,C21*I7,C21*0.5)*12/26 | K21: Total | N21: =IF(R10,L21*Q7,L21*0.5) | P21: =IF(R10,L21*R7,L21*0.5)*12/26
C22: \ | D22: Remainder | E22: =E20-E21 | F22: Remainder | G22: =G20-G21 | L22: \ | M22: Remainder | N22: =N20-N21 | O22: Remainder | P22: =P20-P21
B23: Total | C23: 1500 | D23: Savings | E23: =IF(I10,C23*H7,C23*0.5) | F23: Savings | G23: =IF(I10,C23*I7,C23*0.5)*12/26 | K23: Total | N23: =IF(R10,L23*Q7,L23*0.5) | P23: =IF(R10,L23*R7,L23*0.5)*12/26
C24: \ | D24: Remainder | E24: =E22-E23 | F24: Remainder | G24: =G22-G23 | L24: \ | M24: Remainder | N24: =N22-N23 | O24: Remainder | P24: =P22-P23
B25: Total | C25: 0 | D25: Investments | E25: =IF(I10,C25*H7,C25*0.5) | F25: Investments | G25: =IF(I10,C25*I7,C25*0.5)*12/26 | H25: Roomate Total | I25: =IF(H13,0,SUM(I14:I24)) | K25: Total | N25: =IF(R10,L25*Q7,L25*0.5) | P25: =IF(R10,L25*R7,L25*0.5)*12/26 | Q25: Roomate Total | R25: =IF(Q13,0,SUM(R14:R24))
D26: Remainder | E26: =E24-E25 | F26: Remainder | G26: =G24-G25 | M26: Remainder | N26: =N24-N25 | O26: Remainder | P26: =P24-P25
B27: Total | C27: 100 | D27: Gifts | E27: =IF(I10,C27*H7,C27*0.5) | F27: Gifts | G27: =IF(I10,C27*I7,C27*0.5)*12/26 | H27: Discrepancy | K27: Total | N27: =IF(R10,L27*Q7,L27*0.5) | P27: =IF(R10,L27*R7,L27*0.5)*12/26 | Q27: Discrepancy
D28: Remainder | E28: =E26-E27 | F28: Remainder | G28: =G26-G27 | H28: =(C17-C30)-(E30+(G30*26/12)) | M28: Remainder | N28: =N26-N27 | O28: Remainder | P28: =P26-P27 | Q28: =(L17-L30)-(N30+(P30*26/12))
B29: Total | C29: 300 | D29: FU Money | E29: =IF(I10,C29*H7,C29*0.5) | F29: FU Money | G29: =IF(I10,C29*I7,C29*0.5)*12/26 | K29: Total | N29: =IF(R10,L29*Q7,L29*0.5) | P29: =IF(R10,L29*R7,L29*0.5)*12/26
B30: Total | C30: =SUM(C31:C32) | D30: Remainder | E30: =E28-E29 | F30: Remainder | G30: =G28-G29 | K30: Total | L30: =SUM(L31:L32) | M30: Remainder | N30: =N28-N29 | O30: Remainder | P30: =P28-P29
B31: Expenses | C31: =SUM(E31,(G31*26/12)) | D31: Expenses | E31: =SUM(E19,E21,E16) | F31: Expenses (FN) | G31: =SUM(G19,G21,G16) | K31: Expenses | L31: =SUM(N31,(P31*26/12)) | M31: Expenses | N31: =SUM(N19,N21,N16) | O31: Expenses (FN) | P31: =SUM(P19,P21,P16)
B32: Save & Inv | C32: =SUM(C23,C25,C27,C29) | D32: Saved & Invested | E32: =SUM(E23,E25,E27,E29) | F32: Save& Invest (FN) | G32: =SUM(G23,G25,G27,G29) | K32: Save & Inv | L32: =SUM(L23,L25,L27,L29) | M32: Saved & Invested | N32: =SUM(N23,N25,N27,N29) | O32: Save& Invest (FN) | P32: =SUM(P23,P25,P27,P29)
L34: Accounts | N34: Planning
L35: Offset | M35: =SUM(N27,N25,N23,N16) | N35: 5000
L36: Shared Account | M36: =N21 | N36: =M36
L37: Card | M37: =N19 | N37: 800
L38: FU Money | M38: =N29 | N38: 300
L39: Remainder | M39: =N17-SUM(M35:M38) | N39: =M39+(SUM(M35:M38)-SUM(N35:N38))

Sheet Basic Savings
B2: Saving
B3: Able to save with | C3: No Sacrifice | D3: Super Sacrifice
B4: Month | C4: =G13 | D4: =((Income!H9-C8)/12)+(Income!K8-(Income!K8*0.15)) | F4: Assuming no returns, fees or interest, only initial tax
B5: Year | C5: =C4*12 | D5: =D4*12
B6: 3 Year | C6: =C5*3 | D6: =D5*3
B7: 5 Year | C7: =C5*5 | D7: =D5*5
B8: Yearly Remainder | C8: =Income!H5-(G13*12) | F8: The goal here is keep yearly remainder the same
B10: Savings Split
B11: Total Saved | C11: Held in Bank | D11: Held in Super
B12: Month | C12: =((Income!H9-C8)/12) | D12: =(Income!K8-(Income!K8*0.15)) | F12: Save-able Income
B13: Year | C13: =C12*12 | D13: =D12*12 | F13: Monthly | G13: 0
B14: 3 Year | C14: =C13*3 | D14: =D13*3
B15: 5 Year | C15: =C13*5 | D15: =IF(D13*5>50000,50000,D13*5)
B16: Overflow | C16: =IF(D13*5>50000,(D13*5-50000)+(C13*5),C13*5) | D16: =(D13*5-50000)
B19: Saving
B20: Able to save with | C20: No Sacrifice | D20: Super Sacrifice
B21: Month | C21: =G30 | D21: =((Income!H27-C25)/12)+(Income!K26-(Income!K26*0.15)) | F21: Assuming no returns, fees or interest, only initial tax
B22: Year | C22: =C21*12 | D22: =D21*12
B23: 3 Year | C23: =C22*3 | D23: =D22*3
B24: 5 Year | C24: =C22*5 | D24: =D22*5
B25: Yearly Remainder | C25: =Income!H23-(G30*12) | F25: The goal here is keep yearly remainder the same
B27: Savings Split
B28: Total Saved | C28: Held in Bank | D28: Held in Super
B29: Month | C29: =((Income!H27-C25)/12) | D29: =(Income!K26-(Income!K26*0.15)) | F29: Save-able Income
B30: Year | C30: =C29*12 | D30: =D29*12 | F30: Monthly | G30: 0
B31: 3 Year | C31: =C30*3 | D31: =D30*3
B32: 5 Year | C32: =C30*5 | D32: =IF(D30*5>50000,50000,D30*5)
B33: Overflow | C33: =IF(D30*5>50000,(D30*5-50000)+(C30*5),C30*5) | D33: =(D30*5-50000)

Sheet Advanced Savings
B2: Savings | F2: Bank Interest
B3: Total Saved | C3: No Sacrifice | D3: Super Sacrifice | F3: Annual | G3: 0.05
B4: Month | C4: =IF(F6,(('Basic Savings'!C4)*(1+(G3/12-(G3/12*'Logic Sheet'!B12))))+G12,(('Basic Savings'!C4)*(1+G3/12))+G12) | D4: =SUM(C11:D11)
B5: Year | C5: =IF(F6,(-FV((G3/12-((G3/12)*'Logic Sheet'!B12)),12,('Basic Savings'!C4),G12,1)),(-FV(G3/12,12,('Basic Savings'!C4),G12,1))) | D5: =SUM(C12:D12) | F5: Guess Interest Tax | J5: P1
B6: 3 Year | C6: =IF(F6,(-FV((G3/12-((G3/12)*'Logic Sheet'!B12)),3*12,('Basic Savings'!C4),G12,1)),(-FV(G3/12,3*12,('Basic Savings'!C4),G12,1))) | D6: =SUM(C13:D13) | F6: TRUE
B7: 5 Year | C7: =IF(F6,(-FV((G3/12-((G3/12)*'Logic Sheet'!B12)),5*12,('Basic Savings'!C4),G12,1)),(-FV(G3/12,5*12,('Basic Savings'!C4),G12,1))) | D7: =SUM(C14:D14)
F8: Super Fund
B9: Savings Split | F9: Aware Super
B10: Total Saved | C10: Held in Bank | D10: Held in Super
B11: Month | C11: =IF(F6,(((Income!H9-'Basic Savings'!C8)/12)*(1+(G3/12-(G3/12/100*32.5))))+G12,(((Income!H9-'Basic Savings'!C8)/12)*(1+G3/12))+G12) | D11: =(Income!K8-(Income!K8*0.15)+G14) | F11: Starting Amount
B12: Year | C12: =IF(F6,(-FV((G3/12-((G3/12)*'Logic Sheet'!B12)),12,((Income!H9-'Basic Savings'!C8)/12),G12,1)),(-FV(G3/12,12,((Income!H9-'Basic Savings'!C8)/12),G12,1))) | D12: =IF(-FV('Logic Sheet'!C9/12,12,(Income!K8-(Income!K8*0.15)),G14,1)*'Logic Sheet'!C5+'Logic Sheet'!B5 <'Logic Sheet'!D5,-FV('Logic Sheet'!C9/12,12,(Income!K8-(Income!K8*0.15)),G14,1)-(-FV('Logic Sheet'!C9/12,12,(Income!K8-(Income!K8*0.15)),G14,1)*'Logic Sheet'!C5+'Logic Sheet'!B5),(-FV('Logic Sheet'!C9/12,12,(Income!K8-(Income!K8*0.15)),G14,1)) - 'Logic Sheet'!D5) | F12: Bank | G12: 10000
B13: 3 Year | C13: =IF(F6,(-FV((G3/12-((G3/12)*'Logic Sheet'!B12)),3*12,((Income!H9-'Basic Savings'!C8)/12),G12,1)),(-FV(G3/12,3*12,((Income!H9-'Basic Savings'!C8)/12),G12,1))) | D13: =IF(-FV('Logic Sheet'!D9/12,3*12,(Income!K8-(Income!K8*0.15)),G14,1)*'Logic Sheet'!C5+'Logic Sheet'!B5 <'Logic Sheet'!D5,-FV('Logic Sheet'!D9/12,3*12,(Income!K8-(Income!K8*0.15)),G14,1)-(-FV('Logic Sheet'!D9/12,3*12,(Income!K8-(Income!K8*0.15)),G14,1)*'Logic Sheet'!C5+'Logic Sheet'!B5),(-FV('Logic Sheet'!D9/12,3*12,(Income!K8-(Income!K8*0.15)),G14,1)) - 'Logic Sheet'!D5)
B14: 5 Year | C14: =IF(F6,(-FV((G3/12-((G3/12)*'Logic Sheet'!B12)),5*12,((Income!H9-'Basic Savings'!C8)/12),G12,1)),(-FV(G3/12,5*12,((Income!H9-'Basic Savings'!C8)/12),G12,1))) | D14: =IF(-FV('Logic Sheet'!E9/12,5*12,(Income!K8-(Income!K8*0.15)),G14,1)*'Logic Sheet'!C5+'Logic Sheet'!B5 <'Logic Sheet'!D5,-FV('Logic Sheet'!E9/12,5*12,(Income!K8-(Income!K8*0.15)),G14,1)-(-FV('Logic Sheet'!E9/12,5*12,(Income!K8-(Income!K8*0.15)),G14,1)*'Logic Sheet'!C5+'Logic Sheet'!B5),(-FV('Logic Sheet'!E9/12,5*12,(Income!K8-(Income!K8*0.15)),G14,1)) - 'Logic Sheet'!D5) | F14: Super | G14: 0
B15: Overflow | C15: =IF(D14>50000,(D14-50000)+(C14),C14) | D15: =IF(D14<50000,D14,D14-50000)
B16: Total | C16: =SUM(C14:D14) | D16: + Interest Earned On Excess
B19: Savings | F19: Bank Interest
B20: Total Saved | C20: No Sacrifice | D20: Super Sacrifice | F20: Annual | G20: 0.05
B21: Month | C21: =IF(F23,(('Basic Savings'!C21)*(1+(G20/12-(G20/12*'Logic Sheet'!B29))))+G29,(('Basic Savings'!C21)*(1+G20/12))+G29) | D21: =SUM(C28:D28) | J21: P2
B22: Year | C22: =IF(F23,(-FV((G20/12-((G20/12)*'Logic Sheet'!B29)),12,('Basic Savings'!C21),G29,1)),(-FV(G20/12,12,('Basic Savings'!C21),G29,1))) | D22: =SUM(C29:D29) | F22: Guess Interest Tax
B23: 3 Year | C23: =IF(F23,(-FV((G20/12-((G20/12)*'Logic Sheet'!B29)),3*12,('Basic Savings'!C21),G29,1)),(-FV(G20/12,3*12,('Basic Savings'!C21),G29,1))) | D23: =SUM(C30:D30) | F23: TRUE
B24: 5 Year | C24: =IF(F23,(-FV((G20/12-((G20/12)*'Logic Sheet'!B29)),5*12,('Basic Savings'!C21),G29,1)),(-FV(G20/12,5*12,('Basic Savings'!C21),G29,1))) | D24: =SUM(C31:D31)
F25: Super Fund
B26: Savings Split | F26: Aware Super
B27: Total Saved | C27: Held in Bank | D27: Held in Super
B28: Month | C28: =IF(F23,(((Income!H27-'Basic Savings'!C25)/12)*(1+(G20/12-(G20/12/100*32.5))))+G29,(((Income!H26-'Basic Savings'!C25)/12)*(1+G20/12))+G29) | D28: =(Income!K26-(Income!K26*0.15)+G31) | F28: Starting Amount
B29: Year | C29: =IF(F23,(-FV((G20/12-((G20/12)*'Logic Sheet'!B29)),12,((Income!H26-'Basic Savings'!C25)/12),G29,1)),(-FV(G20/12,12,((Income!H26-'Basic Savings'!C25)/12),G29,1))) | D29: =IF(-FV('Logic Sheet'!C27/12,12,(Income!K26-(Income!K26*0.15)),G31,1)*'Logic Sheet'!C23+'Logic Sheet'!B23 <'Logic Sheet'!D23,-FV('Logic Sheet'!C27/12,12,(Income!K26-(Income!K26*0.15)),G31,1)-(-FV('Logic Sheet'!C27/12,12,(Income!K26-(Income!K26*0.15)),G31,1)*'Logic Sheet'!C23+'Logic Sheet'!B23),(-FV('Logic Sheet'!C27/12,12,(Income!K26-(Income!K26*0.15)),G31,1)) - 'Logic Sheet'!D23) | F29: Bank | G29: 5000
B30: 3 Year | C30: =IF(F23,(-FV((G20/12-((G20/12)*'Logic Sheet'!B29)),3*12,((Income!H26-'Basic Savings'!C25)/12),G29,1)),(-FV(G20/12,3*12,((Income!H26-'Basic Savings'!C25)/12),G29,1))) | D30: =IF(-FV('Logic Sheet'!D27/12,3*12,(Income!K26-(Income!K26*0.15)),G31,1)*'Logic Sheet'!C23+'Logic Sheet'!B23 <'Logic Sheet'!D23,-FV('Logic Sheet'!D27/12,3*12,(Income!K26-(Income!K26*0.15)),G31,1)-(-FV('Logic Sheet'!D27/12,3*12,(Income!K26-(Income!K26*0.15)),G31,1)*'Logic Sheet'!C23+'Logic Sheet'!B23),(-FV('Logic Sheet'!D27/12,3*12,(Income!K26-(Income!K26*0.15)),G31,1)) - 'Logic Sheet'!D23) | J30: Broken
B31: 5 Year | C31: =IF(F23,(-FV((G20/12-((G20/12)*'Logic Sheet'!B29)),5*12,((Income!H26-'Basic Savings'!C25)/12),G29,1)),(-FV(G20/12,5*12,((Income!H26-'Basic Savings'!C25)/12),G29,1))) | D31: =IF(-FV('Logic Sheet'!E27/12,5*12,(Income!K26-(Income!K26*0.15)),G31,1)*'Logic Sheet'!C23+'Logic Sheet'!B23 <'Logic Sheet'!D23,-FV('Logic Sheet'!E27/12,5*12,(Income!K26-(Income!K26*0.15)),G31,1)-(-FV('Logic Sheet'!E27/12,5*12,(Income!K26-(Income!K26*0.15)),G31,1)*'Logic Sheet'!C23+'Logic Sheet'!B23),(-FV('Logic Sheet'!E27/12,5*12,(Income!K26-(Income!K26*0.15)),G31,1)) - 'Logic Sheet'!D23) | F31: Super | G31: 0
B32: Overflow | C32: =IF(D31>50000,(D31-50000)+(C31),C31) | D32: =IF(D31<50000,D31,D31-50000)
B33: Total | C33: =SUM(C31:D31) | D33: + Interest Earned On Excess

Sheet Income
B2: Normal Income
B3: Take Home | C3: Totals | D3: After Super | E3: After Tax | F3: After Hex | G3: LITO | H3: After Medicare | J3: Salary Package
B4: Month | C4: =C5/12 | D4: =D5/12 | E4: =E5/12 | F4: =F5/12 | G4: =G5/12 | H4: =H5/12 | J4: Yearly | K4: 90000
B5: Year | C5: =K4 | D5: =C5/1.115 | E5: =D5-(IF(D5 <= 18200, 0, IF(D5 <= 45000, (D5 - 18200) * 0.16, IF(D5 <= 135000, (D5 - 45000) * 0.3 + 4288, IF(D5 <= 190000, (D5 - 135000) * 0.37 + 31288 , (D5 - 190000) * 0.45 + 51638))))) | F5: =E5 | G5: =F5+IF(D5 <= 37500, 700, IF(D5 <= 45000, 700 - (D5 - 37500) * 0.05, IF(D5 <= 66667, 325 - (D5 - 45000) * 0.015, 0))) | H5: =G5-(D5*0.02)
B6: Reductions | C6: =SUM(E6:H6) | D6: =D5*0.115 | E6: =D5-E5 | F6: =0 | G6: =-IF(D5 <= 37500, 700, IF(D5 <= 45000, 700 - (D5 - 37500) * 0.05, IF(D5 <= 66667, 325 - (D5 - 45000) * 0.015, 0))) | H6: =D5*0.02
B7: After Super Sacrifice | J7: Sacrifice Amount
B8: Month | C8: =C9/12 | D8: =C8/1.115-(K8) | E8: =E9/12 | F8: =F9/12 | G8: =G9/12 | H8: =H9/12 | J8: Monthly | K8: 0
B9: Year | C9: =K4 | D9: =C9/1.115-K8*12 | E9: =D9-(IF(D9 <= 18200, 0, IF(D9 <= 45000, (D9 - 18200) * 0.16, IF(D9 <= 135000, (D9 - 45000) * 0.3 + 4288, IF(D9 <= 190000, (D9 - 135000) * 0.37 + 31288 , (D9 - 190000) * 0.45 + 51667))))) | F9: =E9 | G9: =F9+IF(D9 <= 37500, 700, IF(D9 <= 45000, 700 - (D9 - 37500) * 0.05, IF(D9 <= 66667, 325 - (D9 - 45000) * 0.015, 0))) | H9: =G9-(D9*0.02)
B10: Reductions | C10: =SUM(E10:H10) | D10: =D5*0.115+K8*12 | E10: =(D9-18200-26800)*0.3+4288 | F10: =0 | G10: =-IF(D9 <= 37500, 700, IF(D9 <= 45000, 700 - (D9 - 37500) * 0.05, IF(D9 <= 66667, 325 - (D9 - 45000) * 0.015, 0))) | H10: =D9*0.02
J11: Keep in mind anything above 15K a year cannot be used for the house deposit (1250p/month)
B12: Technically Earned
B13: After Tax | C13: No Super Sacrifice | F13: Super Sacrifice
B14: Month | C14: =C15/12 | F14: =F15/12
B15: Year | C15: =C5-C17 | F15: =C9-F17
B16: Super Tax | C16: =D6*0.15 | F16: =D10*0.15 | J16: P1
B17: Total Tax | C17: =C6+C16 | F17: =C10+F16
B20: Normal Income
B21: Take Home | C21: Totals | D21: After Super | E21: After Tax | F21: After Hex | G21: LITO | H21: After Medicare | J21: Salary Package
B22: Month | C22: =C23/12 | D22: =D23/12 | E22: =E23/12 | F22: =F23/12 | G22: =G23/12 | H22: =H23/12 | J22: Yearly | K22: 70000
B23: Year | C23: =K22 | D23: =C23/1.115 | E23: =D23-(IF(D23 <= 18200, 0, IF(D23 <= 45000, (D23 - 18200) * 0.16, IF(D23 <= 135000, (D23 - 45000) * 0.3 + 4288, IF(D23 <= 190000, (D23 - 135000) * 0.37 + 31288, (D23 - 190000) * 0.45 + 51638))))) | F23: =E23-ROUND(D23*0.035,0) | G23: =F23+IF(D23 <= 37500, 700, IF(D23 <= 45000, 700 - (D23 - 37500) * 0.05, IF(D23 <= 66667, 325 - (D23 - 45000) * 0.015, 0))) | H23: =G23-(D23*0.02)
B24: Reductions | C24: =SUM(E24:H24) | D24: =D23*0.115 | E24: =D23-E23 | F24: =ROUND(D23*0.035,0) | G24: =-IF(D23 <= 37500, 700, IF(D23 <= 45000, 700 - (D23 - 37500) * 0.05, IF(D23 <= 66667, 325 - (D23 - 45000) * 0.015, 0))) | H24: =D23*0.02
B25: After Super Sacrifice | J25: Sacrifice Amount
B26: Month | C26: =C27/12 | D26: =C26/1.115-(K26) | E26: =E27/12 | F26: =F27/12 | G26: =G27/12 | H26: =H27/12 | J26: Monthly | K26: 0
B27: Year | C27: =K22 | D27: =C27/1.115-K26*12 | E27: =D27-(IF(D27 <= 18200, 0, IF(D27 <= 45000, (D27 - 18200) * 0.16, IF(D27 <= 135000, (D27 - 45000) * 0.3 + 4288, IF(D27 <= 190000, (D27 - 135000) * 0.37 + 31288, (D27 - 190000) * 0.45 + 51638))))) | F27: =E27-ROUND(D23*0.035,0) | G27: =F27+IF(D27 <= 37500, 700, IF(D27 <= 45000, 700 - (D27 - 37500) * 0.05, IF(D27 <= 66667, 325 - (D27 - 45000) * 0.015, 0))) | H27: =G27-(D27*0.02)
B28: Reductions | C28: =SUM(E28:H28) | D28: =D23*0.115+K26*12 | E28: =(D27-18200-26800)*0.3+4288 | F28: =ROUND(D23*0.035,0) | G28: =-IF(D27 <= 37500, 700, IF(D27 <= 45000, 700 - (D27 - 37500) * 0.05, IF(D27 <= 66667, 325 - (D27 - 45000) * 0.015, 0))) | H28: =D27*0.02
J29: Keep in mind anything above 15K a year cannot be used for the house deposit (1250p/month)
B30: Technically Earned
B31: After Tax | C31: No Super Sacrifice | F31: Super Sacrifice
B32: Month | C32: =C33/12 | F32: =F33/12
B33: Year | C33: =C23-C35 | F33: =C27-F35
B34: Super Tax | C34: =D24*0.15 | F34: =D28*0.15 | J34: P2
B35: Total Tax | C35: =C24+C34 | F35: =C28+F34

Sheet Housing Costs
B2: Property Value | D2: Estimated Up Front Costs | G2: Savings Account
B3: 600000 | D3: Stamp Duty | E3: =IF(D13,IF(B3<=600000, 0, IF(B3<=750000, (B3-600000)/150000*(2870 + (750000-130000)*0.06) * 0.95, IF(B3<=25000, B3*0.014 * 0.95, IF(B3<=130000, (350 + (B3-25000)*0.024) * 0.95, IF(B3<=960000, (2870 + (B3-130000)*0.06) * 0.95, B3*0.055 * 0.95))))) ,IF(B3<=25000, B3*0.014, IF(B3<=130000, 350 + (B3-25000)*0.024, IF(B3<=960000, 2870 + (B3-130000)*0.06, B3*0.055)))) | G3: =SUM('Advanced Savings'!G12,'Advanced Savings'!G29)
B4: Deposit | C4: Government | D4: Mortgage Rego | E4: 121.4 | G4: Max FHSS Release Ammount
B5: =B3*0.05 | C5: =B3*0 | D5: Transfer Fee | E5: =102.4 + CEILING(B3/1000, 1) * 2.34 | G5: =SUM('Advanced Savings'!G14,'Advanced Savings'!G31)*0.85
B6: Total Deposit | D6: Title Search | E6: 36.2 | G6: Stocks / Investments
B7: =B5+C5 | D7: Conveyancing | E7: 2000 | G7: 0
B8: Loan Required | D8: Total Up-Front Costs | G8: Friend/Fam Gift
B9: =B3-B7 | D9: =SUM(E3:E7,B5) | G9: 0
B10: Loan / Value Ratio | D10: =IF(D11<0,"Missing Liquid Cash","Extra Cash") | G10: Any Extras
B11: =B9/B3 | D11: =B16-D9 | G11: 0
B12: Estimated Repayments | D12: First Home Buyer? | G12: Total Coushion Needed
B13: =PMT(D17 / 12,D15 * 12, -B9) | D13: TRUE | G13: 0
B14: Willing Savings | D14: Loan Term | G14: Total Savings
D15: 30
B16: =G16-G13 | D16: Interest Rate | G16: =SUM(G11,G9,G7,G5,G3)
D17: 0.0549
C19: "Genuine Savings" only taken into account when you select "Using Loan For Extra Costs".

Sheet Super Data
B1: =IFERROR(__xludf.DUMMYFUNCTION("IMPORTRANGE(""https://docs.google.com/spreadsheets/d/1A2a_CIOEK-POlkK616JVZN4ouhsUMkdiZXm1KiJuqJQ/edit#gid=814241220"",""Fees - High Growth!1:40"")"),"Fees - High Growth")
B4: =IFERROR(__xludf.DUMMYFUNCTION("""COMPUTED_VALUE"""),"Super fund") | D4: =IFERROR(__xludf.DUMMYFUNCTION("""COMPUTED_VALUE"""),"Admin fees") | G4: =IFERROR(__xludf.DUMMYFUNCTION("""COMPUTED_VALUE"""),"Investment fees") | I4: =IFERROR(__xludf.DUMMYFUNCTION("""COMPUTED_VALUE"""),"Total fees for a given super balance") | N4: =IFERROR(__xludf.DUMMYFUNCTION("""COMPUTED_VALUE"""),"Equity characteristic") | O4: =IFERROR(__xludf.DUMMYFUNCTION("""COMPUTED_VALUE"""),"Other information")
B5: =IFERROR(__xludf.DUMMYFUNCTION("""COMPUTED_VALUE"""),"Name") | C5: =IFERROR(__xludf.DUMMYFUNCTION("""COMPUTED_VALUE"""),"Type") | D5: =IFERROR(__xludf.DUMMYFUNCTION("""COMPUTED_VALUE"""),"Fixed p.a") | E5: =IFERROR(__xludf.DUMMYFUNCTION("""COMPUTED_VALUE"""),"% of AUM") | F5: =IFERROR(__xludf.DUMMYFUNCTION("""COMPUTED_VALUE"""),"Admin fee cap") | G5: =IFERROR(__xludf.DUMMYFUNCTION("""COMPUTED_VALUE"""),"High Growth") | H5: =IFERROR(__xludf.DUMMYFUNCTION("""COMPUTED_VALUE"""),"Buy/sell spread") | I5: =IFERROR(__xludf.DUMMYFUNCTION("""COMPUTED_VALUE"""),10000.0) | J5: =IFERROR(__xludf.DUMMYFUNCTION("""COMPUTED_VALUE"""),50000.0) | K5: =IFERROR(__xludf.DUMMYFUNCTION("""COMPUTED_VALUE"""),100000.0) | L5: =IFERROR(__xludf.DUMMYFUNCTION("""COMPUTED_VALUE"""),250000.0) | M5: =IFERROR(__xludf.DUMMYFUNCTION("""COMPUTED_VALUE"""),500000.0) | N5: =IFERROR(__xludf.DUMMYFUNCTION("""COMPUTED_VALUE"""),"Active/Passive?") | O5: =IFERROR(__xludf.DUMMYFUNCTION("""COMPUTED_VALUE"""),"Fee Links") | P5: =IFERROR(__xludf.DUMMYFUNCTION("""COMPUTED_VALUE"""),"As at:") | Q5: =IFERROR(__xludf.DUMMYFUNCTION("""COMPUTED_VALUE"""),"Notes")
B6: =IFERROR(__xludf.DUMMYFUNCTION("""COMPUTED_VALUE"""),"Aware Super") | C6: =IFERROR(__xludf.DUMMYFUNCTION("""COMPUTED_VALUE"""),"Industry") | D6: =IFERROR(__xludf.DUMMYFUNCTION("""COMPUTED_VALUE"""),52.0) | E6: =IFERROR(__xludf.DUMMYFUNCTION("""COMPUTED_VALUE"""),0.0015) | F6: =IFERROR(__xludf.DUMMYFUNCTION("""COMPUTED_VALUE"""),750.0) | G6: =IFERROR(__xludf.DUMMYFUNCTION("""COMPUTED_VALUE"""),0.0078) | H6: =IFERROR(__xludf.DUMMYFUNCTION("""COMPUTED_VALUE"""),"Nil") | I6: =IFERROR(__xludf.DUMMYFUNCTION("""COMPUTED_VALUE"""),145.0) | J6: =IFERROR(__xludf.DUMMYFUNCTION("""COMPUTED_VALUE"""),517.0) | K6: =IFERROR(__xludf.DUMMYFUNCTION("""COMPUTED_VALUE"""),982.0) | L6: =IFERROR(__xludf.DUMMYFUNCTION("""COMPUTED_VALUE"""),2377.0) | M6: =IFERROR(__xludf.DUMMYFUNCTION("""COMPUTED_VALUE"""),4702.0) | N6: =IFERROR(__xludf.DUMMYFUNCTION("""COMPUTED_VALUE"""),"Active") | O6: =IFERROR(__xludf.DUMMYFUNCTION("""COMPUTED_VALUE"""),"Aware") | P6: =IFERROR(__xludf.DUMMYFUNCTION("""COMPUTED_VALUE"""),45057.0)
B7: =IFERROR(__xludf.DUMMYFUNCTION("""COMPUTED_VALUE"""),"Aware Super") | C7: =IFERROR(__xludf.DUMMYFUNCTION("""COMPUTED_VALUE"""),"Industry") | D7: =IFERROR(__xludf.DUMMYFUNCTION("""COMPUTED_VALUE"""),52.0) | E7: =IFERROR(__xludf.DUMMYFUNCTION("""COMPUTED_VALUE"""),0.0015) | F7: =IFERROR(__xludf.DUMMYFUNCTION("""COMPUTED_VALUE"""),750.0) | G7: =IFERROR(__xludf.DUMMYFUNCTION("""COMPUTED_VALUE"""),0.001) | H7: =IFERROR(__xludf.DUMMYFUNCTION("""COMPUTED_VALUE"""),"Nil") | I7: =IFERROR(__xludf.DUMMYFUNCTION("""COMPUTED_VALUE"""),77.0) | J7: =IFERROR(__xludf.DUMMYFUNCTION("""COMPUTED_VALUE"""),177.0) | K7: =IFERROR(__xludf.DUMMYFUNCTION("""COMPUTED_VALUE"""),302.0) | L7: =IFERROR(__xludf.DUMMYFUNCTION("""COMPUTED_VALUE"""),677.0) | M7: =IFERROR(__xludf.DUMMYFUNCTION("""COMPUTED_VALUE"""),1302.0) | N7: =IFERROR(__xludf.DUMMYFUNCTION("""COMPUTED_VALUE"""),"Passive") | O7: =IFERROR(__xludf.DUMMYFUNCTION("""COMPUTED_VALUE"""),"Aware") | P7: =IFERROR(__xludf.DUMMYFUNCTION("""COMPUTED_VALUE"""),44742.0)
B8: =IFERROR(__xludf.DUMMYFUNCTION("""COMPUTED_VALUE"""),"ART") | C8: =IFERROR(__xludf.DUMMYFUNCTION("""COMPUTED_VALUE"""),"Industry") | D8: =IFERROR(__xludf.DUMMYFUNCTION("""COMPUTED_VALUE"""),62.4) | E8: =IFERROR(__xludf.DUMMYFUNCTION("""COMPUTED_VALUE"""),0.001) | F8: =IFERROR(__xludf.DUMMYFUNCTION("""COMPUTED_VALUE"""),800.0) | G8: =IFERROR(__xludf.DUMMYFUNCTION("""COMPUTED_VALUE"""),0.0088) | H8: =IFERROR(__xludf.DUMMYFUNCTION("""COMPUTED_VALUE"""),"Nil") | I8: =IFERROR(__xludf.DUMMYFUNCTION("""COMPUTED_VALUE"""),160.4) | J8: =IFERROR(__xludf.DUMMYFUNCTION("""COMPUTED_VALUE"""),552.4) | K8: =IFERROR(__xludf.DUMMYFUNCTION("""COMPUTED_VALUE"""),1042.4) | L8: =IFERROR(__xludf.DUMMYFUNCTION("""COMPUTED_VALUE"""),2512.4) | M8: =IFERROR(__xludf.DUMMYFUNCTION("""COMPUTED_VALUE"""),4962.4) | N8: =IFERROR(__xludf.DUMMYFUNCTION("""COMPUTED_VALUE"""),"Active") | O8: =IFERROR(__xludf.DUMMYFUNCTION("""COMPUTED_VALUE"""),"ART") | P8: =IFERROR(__xludf.DUMMYFUNCTION("""COMPUTED_VALUE"""),45107.0)
B9: =IFERROR(__xludf.DUMMYFUNCTION("""COMPUTED_VALUE"""),"Qsuper") | C9: =IFERROR(__xludf.DUMMYFUNCTION("""COMPUTED_VALUE"""),"Public sector") | D9: =IFERROR(__xludf.DUMMYFUNCTION("""COMPUTED_VALUE"""),0.0) | E9: =IFERROR(__xludf.DUMMYFUNCTION("""COMPUTED_VALUE"""),0.0015) | F9: =IFERROR(__xludf.DUMMYFUNCTION("""COMPUTED_VALUE"""),875.0) | G9: =IFERROR(__xludf.DUMMYFUNCTION("""COMPUTED_VALUE"""),0.007) | H9: =IFERROR(__xludf.DUMMYFUNCTION("""COMPUTED_VALUE"""),"Nil") | I9: =IFERROR(__xludf.DUMMYFUNCTION("""COMPUTED_VALUE"""),85.0) | J9: =IFERROR(__xludf.DUMMYFUNCTION("""COMPUTED_VALUE"""),425.0) | K9: =IFERROR(__xludf.DUMMYFUNCTION("""COMPUTED_VALUE"""),850.0) | L9: =IFERROR(__xludf.DUMMYFUNCTION("""COMPUTED_VALUE"""),2125.0) | M9: =IFERROR(__xludf.DUMMYFUNCTION("""COMPUTED_VALUE"""),4250.0) | N9: =IFERROR(__xludf.DUMMYFUNCTION("""COMPUTED_VALUE"""),"Active") | O9: =IFERROR(__xludf.DUMMYFUNCTION("""COMPUTED_VALUE"""),"Qsuper") | P9: =IFERROR(__xludf.DUMMYFUNCTION("""COMPUTED_VALUE"""),45107.0) | Q9: =IFERROR(__xludf.DUMMYFUNCTION("""COMPUTED_VALUE"""),"* Only open for people working for the QLD Government, or if you're a spouse or child (under 25) of a Qsuper member * Excludes companies involved in manufacturing cigarettes and other tobacco products, cluster munitions, or landmines")
B10: =IFERROR(__xludf.DUMMYFUNCTION("""COMPUTED_VALUE"""),"Hostplus") | C10: =IFERROR(__xludf.DUMMYFUNCTION("""COMPUTED_VALUE"""),"Industry") | D10: =IFERROR(__xludf.DUMMYFUNCTION("""COMPUTED_VALUE"""),78.0) | E10: =IFERROR(__xludf.DUMMYFUNCTION("""COMPUTED_VALUE"""),1.65E-4) | F10: =IFERROR(__xludf.DUMMYFUNCTION("""COMPUTED_VALUE"""),"NA") | G10: =IFERROR(__xludf.DUMMYFUNCTION("""COMPUTED_VALUE"""),0.0086) | H10: =IFERROR(__xludf.DUMMYFUNCTION("""COMPUTED_VALUE"""),"Nil") | I10: =IFERROR(__xludf.DUMMYFUNCTION("""COMPUTED_VALUE"""),165.65) | J10: =IFERROR(__xludf.DUMMYFUNCTION("""COMPUTED_VALUE"""),516.25) | K10: =IFERROR(__xludf.DUMMYFUNCTION("""COMPUTED_VALUE"""),954.5) | L10: =IFERROR(__xludf.DUMMYFUNCTION("""COMPUTED_VALUE"""),2269.25) | M10: =IFERROR(__xludf.DUMMYFUNCTION("""COMPUTED_VALUE"""),4460.5) | N10: =IFERROR(__xludf.DUMMYFUNCTION("""COMPUTED_VALUE"""),"Active") | O10: =IFERROR(__xludf.DUMMYFUNCTION("""COMPUTED_VALUE"""),"Hostplus") | P10: =IFERROR(__xludf.DUMMYFUNCTION("""COMPUTED_VALUE"""),45107.0) | Q10: =IFERROR(__xludf.DUMMYFUNCTION("""COMPUTED_VALUE"""),"ESG Integration")
B11: =IFERROR(__xludf.DUMMYFUNCTION("""COMPUTED_VALUE"""),"Rest") | C11: =IFERROR(__xludf.DUMMYFUNCTION("""COMPUTED_VALUE"""),"Industry") | D11: =IFERROR(__xludf.DUMMYFUNCTION("""COMPUTED_VALUE"""),78.0) | E11: =IFERROR(__xludf.DUMMYFUNCTION("""COMPUTED_VALUE"""),0.001) | F11: =IFERROR(__xludf.DUMMYFUNCTION("""COMPUTED_VALUE"""),300.0) | G11: =IFERROR(__xludf.DUMMYFUNCTION("""COMPUTED_VALUE"""),0.0075) | H11: =IFERROR(__xludf.DUMMYFUNCTION("""COMPUTED_VALUE"""),"0.07% / 0%") | I11: =IFERROR(__xludf.DUMMYFUNCTION("""COMPUTED_VALUE"""),163.0) | J11: =IFERROR(__xludf.DUMMYFUNCTION("""COMPUTED_VALUE"""),503.0) | K11: =IFERROR(__xludf.DUMMYFUNCTION("""COMPUTED_VALUE"""),928.0) | L11: =IFERROR(__xludf.DUMMYFUNCTION("""COMPUTED_VALUE"""),2203.0) | M11: =IFERROR(__xludf.DUMMYFUNCTION("""COMPUTED_VALUE"""),4128.0) | N11: =IFERROR(__xludf.DUMMYFUNCTION("""COMPUTED_VALUE"""),"Active") | O11: =IFERROR(__xludf.DUMMYFUNCTION("""COMPUTED_VALUE"""),"Rest ") | P11: =IFERROR(__xludf.DUMMYFUNCTION("""COMPUTED_VALUE"""),44742.0) | Q11: =IFERROR(__xludf.DUMMYFUNCTION("""COMPUTED_VALUE"""),"* ESG Integration Excludes: * Tobacco and controversial wepaons * >10% from thermal coal mining unless certain climate-related critera are met ")
B12: =IFERROR(__xludf.DUMMYFUNCTION("""COMPUTED_VALUE"""),"Brighter Super") | C12: =IFERROR(__xludf.DUMMYFUNCTION("""COMPUTED_VALUE"""),"Industry") | D12: =IFERROR(__xludf.DUMMYFUNCTION("""COMPUTED_VALUE"""),0.0) | E12: =IFERROR(__xludf.DUMMYFUNCTION("""COMPUTED_VALUE"""),0.0018) | F12: =IFERROR(__xludf.DUMMYFUNCTION("""COMPUTED_VALUE"""),900.0) | G12: =IFERROR(__xludf.DUMMYFUNCTION("""COMPUTED_VALUE"""),0.0074) | H12: =IFERROR(__xludf.DUMMYFUNCTION("""COMPUTED_VALUE"""),"Nil") | I12: =IFERROR(__xludf.DUMMYFUNCTION("""COMPUTED_VALUE"""),92.0) | J12: =IFERROR(__xludf.DUMMYFUNCTION("""COMPUTED_VALUE"""),460.0) | K12: =IFERROR(__xludf.DUMMYFUNCTION("""COMPUTED_VALUE"""),920.0) | L12: =IFERROR(__xludf.DUMMYFUNCTION("""COMPUTED_VALUE"""),2300.0) | M12: =IFERROR(__xludf.DUMMYFUNCTION("""COMPUTED_VALUE"""),4600.0) | N12: =IFERROR(__xludf.DUMMYFUNCTION("""COMPUTED_VALUE"""),"Active") | O12: =IFERROR(__xludf.DUMMYFUNCTION("""COMPUTED_VALUE"""),"Brighter Super") | P12: =IFERROR(__xludf.DUMMYFUNCTION("""COMPUTED_VALUE"""),45107.0) | Q12: =IFERROR(__xludf.DUMMYFUNCTION("""COMPUTED_VALUE"""),"ESG Integration")
B13: =IFERROR(__xludf.DUMMYFUNCTION("""COMPUTED_VALUE"""),"Australian Super") | C13: =IFERROR(__xludf.DUMMYFUNCTION("""COMPUTED_VALUE"""),"Industry") | D13: =IFERROR(__xludf.DUMMYFUNCTION("""COMPUTED_VALUE"""),52.0) | E13: =IFERROR(__xludf.DUMMYFUNCTION("""COMPUTED_VALUE"""),0.001) | F13: =IFERROR(__xludf.DUMMYFUNCTION("""COMPUTED_VALUE"""),350.0) | G13: =IFERROR(__xludf.DUMMYFUNCTION("""COMPUTED_VALUE"""),0.0055) | H13: =IFERROR(__xludf.DUMMYFUNCTION("""COMPUTED_VALUE"""),"Nil") | I13: =IFERROR(__xludf.DUMMYFUNCTION("""COMPUTED_VALUE"""),117.0) | J13: =IFERROR(__xludf.DUMMYFUNCTION("""COMPUTED_VALUE"""),377.0) | K13: =IFERROR(__xludf.DUMMYFUNCTION("""COMPUTED_VALUE"""),702.0) | L13: =IFERROR(__xludf.DUMMYFUNCTION("""COMPUTED_VALUE"""),1677.0) | M13: =IFERROR(__xludf.DUMMYFUNCTION("""COMPUTED_VALUE"""),3152.0) | N13: =IFERROR(__xludf.DUMMYFUNCTION("""COMPUTED_VALUE"""),"Active") | O13: =IFERROR(__xludf.DUMMYFUNCTION("""COMPUTED_VALUE"""),"Australian") | P13: =IFERROR(__xludf.DUMMYFUNCTION("""COMPUTED_VALUE"""),45107.0) | Q13: =IFERROR(__xludf.DUMMYFUNCTION("""COMPUTED_VALUE"""),"ESG Integration")
B14: =IFERROR(__xludf.DUMMYFUNCTION("""COMPUTED_VALUE"""),"UniSuper") | C14: =IFERROR(__xludf.DUMMYFUNCTION("""COMPUTED_VALUE"""),"Industry") | D14: =IFERROR(__xludf.DUMMYFUNCTION("""COMPUTED_VALUE"""),0.0) | E14: =IFERROR(__xludf.DUMMYFUNCTION("""COMPUTED_VALUE"""),0.02) | F14: =IFERROR(__xludf.DUMMYFUNCTION("""COMPUTED_VALUE"""),96.0) | G14: =IFERROR(__xludf.DUMMYFUNCTION("""COMPUTED_VALUE"""),0.0061) | H14: =IFERROR(__xludf.DUMMYFUNCTION("""COMPUTED_VALUE"""),"Nil") | I14: =IFERROR(__xludf.DUMMYFUNCTION("""COMPUTED_VALUE"""),157.0) | J14: =IFERROR(__xludf.DUMMYFUNCTION("""COMPUTED_VALUE"""),401.0) | K14: =IFERROR(__xludf.DUMMYFUNCTION("""COMPUTED_VALUE"""),706.0) | L14: =IFERROR(__xludf.DUMMYFUNCTION("""COMPUTED_VALUE"""),1621.0) | M14: =IFERROR(__xludf.DUMMYFUNCTION("""COMPUTED_VALUE"""),3146.0) | N14: =IFERROR(__xludf.DUMMYFUNCTION("""COMPUTED_VALUE"""),"Active") | O14: =IFERROR(__xludf.DUMMYFUNCTION("""COMPUTED_VALUE"""),"Unisuper") | P14: =IFERROR(__xludf.DUMMYFUNCTION("""COMPUTED_VALUE"""),44742.0) | Q14: =IFERROR(__xludf.DUMMYFUNCTION("""COMPUTED_VALUE"""),"* ESG Integration Excludes: * Tobacco * Companies deriving over 10% of their revenue from thermal coal extraction * Direct investments into live animal export.")
B15: =IFERROR(__xludf.DUMMYFUNCTION("""COMPUTED_VALUE"""),"HESTA") | C15: =IFERROR(__xludf.DUMMYFUNCTION("""COMPUTED_VALUE"""),"Industry") | D15: =IFERROR(__xludf.DUMMYFUNCTION("""COMPUTED_VALUE"""),52.0) | E15: =IFERROR(__xludf.DUMMYFUNCTION("""COMPUTED_VALUE"""),0.0015) | F15: =IFERROR(__xludf.DUMMYFUNCTION("""COMPUTED_VALUE"""),750.0) | G15: =IFERROR(__xludf.DUMMYFUNCTION("""COMPUTED_VALUE"""),0.0083) | H15: =IFERROR(__xludf.DUMMYFUNCTION("""COMPUTED_VALUE"""),"Nil") | I15: =IFERROR(__xludf.DUMMYFUNCTION("""COMPUTED_VALUE"""),150.0) | J15: =IFERROR(__xludf.DUMMYFUNCTION("""COMPUTED_VALUE"""),542.0) | K15: =IFERROR(__xludf.DUMMYFUNCTION("""COMPUTED_VALUE"""),1032.0) | L15: =IFERROR(__xludf.DUMMYFUNCTION("""COMPUTED_VALUE"""),2502.0) | M15: =IFERROR(__xludf.DUMMYFUNCTION("""COMPUTED_VALUE"""),4952.0) | N15: =IFERROR(__xludf.DUMMYFUNCTION("""COMPUTED_VALUE"""),"Active") | O15: =IFERROR(__xludf.DUMMYFUNCTION("""COMPUTED_VALUE"""),"HESTA") | P15: =IFERROR(__xludf.DUMMYFUNCTION("""COMPUTED_VALUE"""),45107.0)
B16: =IFERROR(__xludf.DUMMYFUNCTION("""COMPUTED_VALUE"""),"CareSuper") | C16: =IFERROR(__xludf.DUMMYFUNCTION("""COMPUTED_VALUE"""),"Industry") | D16: =IFERROR(__xludf.DUMMYFUNCTION("""COMPUTED_VALUE"""),78.0) | E16: =IFERROR(__xludf.DUMMYFUNCTION("""COMPUTED_VALUE"""),0.0019) | F16: =IFERROR(__xludf.DUMMYFUNCTION("""COMPUTED_VALUE"""),750.0) | G16: =IFERROR(__xludf.DUMMYFUNCTION("""COMPUTED_VALUE"""),0.0071) | H16: =IFERROR(__xludf.DUMMYFUNCTION("""COMPUTED_VALUE"""),"0.06% / 0.06%") | I16: =IFERROR(__xludf.DUMMYFUNCTION("""COMPUTED_VALUE"""),168.0) | J16: =IFERROR(__xludf.DUMMYFUNCTION("""COMPUTED_VALUE"""),528.0) | K16: =IFERROR(__xludf.DUMMYFUNCTION("""COMPUTED_VALUE"""),978.0) | L16: =IFERROR(__xludf.DUMMYFUNCTION("""COMPUTED_VALUE"""),2328.0) | M16: =IFERROR(__xludf.DUMMYFUNCTION("""COMPUTED_VALUE"""),4378.0) | N16: =IFERROR(__xludf.DUMMYFUNCTION("""COMPUTED_VALUE"""),"Active") | O16: =IFERROR(__xludf.DUMMYFUNCTION("""COMPUTED_VALUE"""),"CareSuper") | P16: =IFERROR(__xludf.DUMMYFUNCTION("""COMPUTED_VALUE"""),45017.0)
B17: =IFERROR(__xludf.DUMMYFUNCTION("""COMPUTED_VALUE"""),"Cbus") | C17: =IFERROR(__xludf.DUMMYFUNCTION("""COMPUTED_VALUE"""),"Industry") | D17: =IFERROR(__xludf.DUMMYFUNCTION("""COMPUTED_VALUE"""),78.0) | E17: =IFERROR(__xludf.DUMMYFUNCTION("""COMPUTED_VALUE"""),0.0019) | F17: =IFERROR(__xludf.DUMMYFUNCTION("""COMPUTED_VALUE"""),1000.0) | G17: =IFERROR(__xludf.DUMMYFUNCTION("""COMPUTED_VALUE"""),0.0066) | H17: =IFERROR(__xludf.DUMMYFUNCTION("""COMPUTED_VALUE"""),"Nil") | I17: =IFERROR(__xludf.DUMMYFUNCTION("""COMPUTED_VALUE"""),163.0) | J17: =IFERROR(__xludf.DUMMYFUNCTION("""COMPUTED_VALUE"""),503.0) | K17: =IFERROR(__xludf.DUMMYFUNCTION("""COMPUTED_VALUE"""),928.0) | L17: =IFERROR(__xludf.DUMMYFUNCTION("""COMPUTED_VALUE"""),2203.0) | M17: =IFERROR(__xludf.DUMMYFUNCTION("""COMPUTED_VALUE"""),4328.0) | N17: =IFERROR(__xludf.DUMMYFUNCTION("""COMPUTED_VALUE"""),"Active") | O17: =IFERROR(__xludf.DUMMYFUNCTION("""COMPUTED_VALUE"""),"Cbus") | P17: =IFERROR(__xludf.DUMMYFUNCTION("""COMPUTED_VALUE"""),44834.0)
B18: =IFERROR(__xludf.DUMMYFUNCTION("""COMPUTED_VALUE"""),"Spirit") | C18: =IFERROR(__xludf.DUMMYFUNCTION("""COMPUTED_VALUE"""),"Industry") | D18: =IFERROR(__xludf.DUMMYFUNCTION("""COMPUTED_VALUE"""),67.6) | E18: =IFERROR(__xludf.DUMMYFUNCTION("""COMPUTED_VALUE"""),0.0015) | F18: =IFERROR(__xludf.DUMMYFUNCTION("""COMPUTED_VALUE"""),450.0) | G18: =IFERROR(__xludf.DUMMYFUNCTION("""COMPUTED_VALUE"""),0.0064) | H18: =IFERROR(__xludf.DUMMYFUNCTION("""COMPUTED_VALUE"""),"Nil") | I18: =IFERROR(__xludf.DUMMYFUNCTION("""COMPUTED_VALUE"""),146.6) | J18: =IFERROR(__xludf.DUMMYFUNCTION("""COMPUTED_VALUE"""),462.6) | K18: =IFERROR(__xludf.DUMMYFUNCTION("""COMPUTED_VALUE"""),857.6) | L18: =IFERROR(__xludf.DUMMYFUNCTION("""COMPUTED_VALUE"""),2042.6) | M18: =IFERROR(__xludf.DUMMYFUNCTION("""COMPUTED_VALUE"""),3717.6) | N18: =IFERROR(__xludf.DUMMYFUNCTION("""COMPUTED_VALUE"""),"Active") | O18: =IFERROR(__xludf.DUMMYFUNCTION("""COMPUTED_VALUE"""),"Spirit") | P18: =IFERROR(__xludf.DUMMYFUNCTION("""COMPUTED_VALUE"""),45107.0)
B19: =IFERROR(__xludf.DUMMYFUNCTION("""COMPUTED_VALUE"""),"Catholic Super") | C19: =IFERROR(__xludf.DUMMYFUNCTION("""COMPUTED_VALUE"""),"Industry") | D19: =IFERROR(__xludf.DUMMYFUNCTION("""COMPUTED_VALUE"""),52.0) | E19: =IFERROR(__xludf.DUMMYFUNCTION("""COMPUTED_VALUE"""),0.0022) | F19: =IFERROR(__xludf.DUMMYFUNCTION("""COMPUTED_VALUE"""),1100.0) | G19: =IFERROR(__xludf.DUMMYFUNCTION("""COMPUTED_VALUE"""),0.0065) | H19: =IFERROR(__xludf.DUMMYFUNCTION("""COMPUTED_VALUE"""),"Nil") | I19: =IFERROR(__xludf.DUMMYFUNCTION("""COMPUTED_VALUE"""),139.0) | J19: =IFERROR(__xludf.DUMMYFUNCTION("""COMPUTED_VALUE"""),487.0) | K19: =IFERROR(__xludf.DUMMYFUNCTION("""COMPUTED_VALUE"""),922.0) | L19: =IFERROR(__xludf.DUMMYFUNCTION("""COMPUTED_VALUE"""),2227.0) | M19: =IFERROR(__xludf.DUMMYFUNCTION("""COMPUTED_VALUE"""),4402.0) | N19: =IFERROR(__xludf.DUMMYFUNCTION("""COMPUTED_VALUE"""),"Active") | O19: =IFERROR(__xludf.DUMMYFUNCTION("""COMPUTED_VALUE"""),"Catholic Super") | P19: =IFERROR(__xludf.DUMMYFUNCTION("""COMPUTED_VALUE"""),45107.0)
B20: =IFERROR(__xludf.DUMMYFUNCTION("""COMPUTED_VALUE"""),"Legal Super") | C20: =IFERROR(__xludf.DUMMYFUNCTION("""COMPUTED_VALUE"""),"Industry") | D20: =IFERROR(__xludf.DUMMYFUNCTION("""COMPUTED_VALUE"""),67.6) | E20: =IFERROR(__xludf.DUMMYFUNCTION("""COMPUTED_VALUE"""),0.0029) | F20: =IFERROR(__xludf.DUMMYFUNCTION("""COMPUTED_VALUE"""),"NA") | G20: =IFERROR(__xludf.DUMMYFUNCTION("""COMPUTED_VALUE"""),0.0063) | H20: =IFERROR(__xludf.DUMMYFUNCTION("""COMPUTED_VALUE"""),"0.07% / 0.08%") | I20: =IFERROR(__xludf.DUMMYFUNCTION("""COMPUTED_VALUE"""),159.6) | J20: =IFERROR(__xludf.DUMMYFUNCTION("""COMPUTED_VALUE"""),527.6) | K20: =IFERROR(__xludf.DUMMYFUNCTION("""COMPUTED_VALUE"""),987.6) | L20: =IFERROR(__xludf.DUMMYFUNCTION("""COMPUTED_VALUE"""),2367.6) | M20: =IFERROR(__xludf.DUMMYFUNCTION("""COMPUTED_VALUE"""),4667.6) | N20: =IFERROR(__xludf.DUMMYFUNCTION("""COMPUTED_VALUE"""),"Active") | O20: =IFERROR(__xludf.DUMMYFUNCTION("""COMPUTED_VALUE"""),"Legal Super") | P20: =IFERROR(__xludf.DUMMYFUNCTION("""COMPUTED_VALUE"""),45107.0)
B21: =IFERROR(__xludf.DUMMYFUNCTION("""COMPUTED_VALUE"""),"Prime Super") | C21: =IFERROR(__xludf.DUMMYFUNCTION("""COMPUTED_VALUE"""),"Industry") | D21: =IFERROR(__xludf.DUMMYFUNCTION("""COMPUTED_VALUE"""),67.6) | E21: =IFERROR(__xludf.DUMMYFUNCTION("""COMPUTED_VALUE"""),0.005) | F21: =IFERROR(__xludf.DUMMYFUNCTION("""COMPUTED_VALUE"""),500.0) | G21: =IFERROR(__xludf.DUMMYFUNCTION("""COMPUTED_VALUE"""),0.0055) | H21: =IFERROR(__xludf.DUMMYFUNCTION("""COMPUTED_VALUE"""),"Nil") | I21: =IFERROR(__xludf.DUMMYFUNCTION("""COMPUTED_VALUE"""),172.6) | J21: =IFERROR(__xludf.DUMMYFUNCTION("""COMPUTED_VALUE"""),592.6) | K21: =IFERROR(__xludf.DUMMYFUNCTION("""COMPUTED_VALUE"""),1117.6) | L21: =IFERROR(__xludf.DUMMYFUNCTION("""COMPUTED_VALUE"""),1942.6) | M21: =IFERROR(__xludf.DUMMYFUNCTION("""COMPUTED_VALUE"""),3317.6) | N21: =IFERROR(__xludf.DUMMYFUNCTION("""COMPUTED_VALUE"""),"Active") | O21: =IFERROR(__xludf.DUMMYFUNCTION("""COMPUTED_VALUE"""),"Prime Super") | P21: =IFERROR(__xludf.DUMMYFUNCTION("""COMPUTED_VALUE"""),44835.0)
B22: =IFERROR(__xludf.DUMMYFUNCTION("""COMPUTED_VALUE"""),"Australian Ethical") | C22: =IFERROR(__xludf.DUMMYFUNCTION("""COMPUTED_VALUE"""),"Retail") | D22: =IFERROR(__xludf.DUMMYFUNCTION("""COMPUTED_VALUE"""),59.13) | E22: =IFERROR(__xludf.DUMMYFUNCTION("""COMPUTED_VALUE"""),0.0023) | F22: =IFERROR(__xludf.DUMMYFUNCTION("""COMPUTED_VALUE"""),"NA") | G22: =IFERROR(__xludf.DUMMYFUNCTION("""COMPUTED_VALUE"""),0.01) | H22: =IFERROR(__xludf.DUMMYFUNCTION("""COMPUTED_VALUE"""),"0.05% / 0.05%") | I22: =IFERROR(__xludf.DUMMYFUNCTION("""COMPUTED_VALUE"""),182.13) | J22: =IFERROR(__xludf.DUMMYFUNCTION("""COMPUTED_VALUE"""),674.13) | K22: =IFERROR(__xludf.DUMMYFUNCTION("""COMPUTED_VALUE"""),1289.13) | L22: =IFERROR(__xludf.DUMMYFUNCTION("""COMPUTED_VALUE"""),3134.13) | M22: =IFERROR(__xludf.DUMMYFUNCTION("""COMPUTED_VALUE"""),6209.13) | N22: =IFERROR(__xludf.DUMMYFUNCTION("""COMPUTED_VALUE"""),"Active") | O22: =IFERROR(__xludf.DUMMYFUNCTION("""COMPUTED_VALUE"""),"Australian Ethical") | P22: =IFERROR(__xludf.DUMMYFUNCTION("""COMPUTED_VALUE"""),44896.0) | Q22: =IFERROR(__xludf.DUMMYFUNCTION("""COMPUTED_VALUE"""),"Fee discounts for balances <$250,000 (does not include the Balanced option). Read the link for more info.")
B23: =IFERROR(__xludf.DUMMYFUNCTION("""COMPUTED_VALUE"""),"Future") | C23: =IFERROR(__xludf.DUMMYFUNCTION("""COMPUTED_VALUE"""),"Retail") | D23: =IFERROR(__xludf.DUMMYFUNCTION("""COMPUTED_VALUE"""),60.0) | E23: =IFERROR(__xludf.DUMMYFUNCTION("""COMPUTED_VALUE"""),0.00513) | F23: =IFERROR(__xludf.DUMMYFUNCTION("""COMPUTED_VALUE"""),"NA") | G23: =IFERROR(__xludf.DUMMYFUNCTION("""COMPUTED_VALUE"""),0.00872) | H23: =IFERROR(__xludf.DUMMYFUNCTION("""COMPUTED_VALUE"""),"0.075% / 0.075%") | I23: =IFERROR(__xludf.DUMMYFUNCTION("""COMPUTED_VALUE"""),198.5) | J23: =IFERROR(__xludf.DUMMYFUNCTION("""COMPUTED_VALUE"""),752.5) | K23: =IFERROR(__xludf.DUMMYFUNCTION("""COMPUTED_VALUE"""),1445.0) | L23: =IFERROR(__xludf.DUMMYFUNCTION("""COMPUTED_VALUE"""),3522.5) | M23: =IFERROR(__xludf.DUMMYFUNCTION("""COMPUTED_VALUE"""),6985.0) | N23: =IFERROR(__xludf.DUMMYFUNCTION("""COMPUTED_VALUE"""),"Active") | O23: =IFERROR(__xludf.DUMMYFUNCTION("""COMPUTED_VALUE"""),"Future") | P23: =IFERROR(__xludf.DUMMYFUNCTION("""COMPUTED_VALUE"""),45107.0)
B24: =IFERROR(__xludf.DUMMYFUNCTION("""COMPUTED_VALUE"""),"Colonial First State") | C24: =IFERROR(__xludf.DUMMYFUNCTION("""COMPUTED_VALUE"""),"Retail") | D24: =IFERROR(__xludf.DUMMYFUNCTION("""COMPUTED_VALUE"""),0.0) | E24: =IFERROR(__xludf.DUMMYFUNCTION("""COMPUTED_VALUE"""),0.002) | F24: =IFERROR(__xludf.DUMMYFUNCTION("""COMPUTED_VALUE"""),"NA") | G24: =IFERROR(__xludf.DUMMYFUNCTION("""COMPUTED_VALUE"""),0.0101) | H24: =IFERROR(__xludf.DUMMYFUNCTION("""COMPUTED_VALUE"""),"0.15% / 0.15%") | I24: =IFERROR(__xludf.DUMMYFUNCTION("""COMPUTED_VALUE"""),121.0) | J24: =IFERROR(__xludf.DUMMYFUNCTION("""COMPUTED_VALUE"""),605.0) | K24: =IFERROR(__xludf.DUMMYFUNCTION("""COMPUTED_VALUE"""),1210.0) | L24: =IFERROR(__xludf.DUMMYFUNCTION("""COMPUTED_VALUE"""),3025.0) | M24: =IFERROR(__xludf.DUMMYFUNCTION("""COMPUTED_VALUE"""),6050.0) | N24: =IFERROR(__xludf.DUMMYFUNCTION("""COMPUTED_VALUE"""),"Active") | O24: =IFERROR(__xludf.DUMMYFUNCTION("""COMPUTED_VALUE"""),"CFS") | P24: =IFERROR(__xludf.DUMMYFUNCTION("""COMPUTED_VALUE"""),45068.0) | Q24: =IFERROR(__xludf.DUMMYFUNCTION("""COMPUTED_VALUE"""),"Option from FirstChoice Multi-manager multi-sector. Portfolio rebates for balances above $100,000. Read the link for more info.")
B25: =IFERROR(__xludf.DUMMYFUNCTION("""COMPUTED_VALUE"""),"Colonial First State") | C25: =IFERROR(__xludf.DUMMYFUNCTION("""COMPUTED_VALUE"""),"Retail") | D25: =IFERROR(__xludf.DUMMYFUNCTION("""COMPUTED_VALUE"""),0.0) | E25: =IFERROR(__xludf.DUMMYFUNCTION("""COMPUTED_VALUE"""),0.002) | F25: =IFERROR(__xludf.DUMMYFUNCTION("""COMPUTED_VALUE"""),"NA") | G25: =IFERROR(__xludf.DUMMYFUNCTION("""COMPUTED_VALUE"""),0.006) | H25: =IFERROR(__xludf.DUMMYFUNCTION("""COMPUTED_VALUE"""),"0.10% / 0.10%") | I25: =IFERROR(__xludf.DUMMYFUNCTION("""COMPUTED_VALUE"""),80.0) | J25: =IFERROR(__xludf.DUMMYFUNCTION("""COMPUTED_VALUE"""),400.0) | K25: =IFERROR(__xludf.DUMMYFUNCTION("""COMPUTED_VALUE"""),800.0) | L25: =IFERROR(__xludf.DUMMYFUNCTION("""COMPUTED_VALUE"""),2000.0) | M25: =IFERROR(__xludf.DUMMYFUNCTION("""COMPUTED_VALUE"""),4000.0) | N25: =IFERROR(__xludf.DUMMYFUNCTION("""COMPUTED_VALUE"""),"Passive") | O25: =IFERROR(__xludf.DUMMYFUNCTION("""COMPUTED_VALUE"""),"CFS") | P25: =IFERROR(__xludf.DUMMYFUNCTION("""COMPUTED_VALUE"""),45068.0) | Q25: =IFERROR(__xludf.DUMMYFUNCTION("""COMPUTED_VALUE"""),"Option from Colonial First State Enhanced Index Series (includes alternative assets). Portfolio rebates for balances above $100,000. Read the link for more info.")
B26: =IFERROR(__xludf.DUMMYFUNCTION("""COMPUTED_VALUE"""),"Colonial First State") | C26: =IFERROR(__xludf.DUMMYFUNCTION("""COMPUTED_VALUE"""),"Retail") | D26: =IFERROR(__xludf.DUMMYFUNCTION("""COMPUTED_VALUE"""),0.0) | E26: =IFERROR(__xludf.DUMMYFUNCTION("""COMPUTED_VALUE"""),0.002) | F26: =IFERROR(__xludf.DUMMYFUNCTION("""COMPUTED_VALUE"""),"NA") | G26: =IFERROR(__xludf.DUMMYFUNCTION("""COMPUTED_VALUE"""),0.0014) | H26: =IFERROR(__xludf.DUMMYFUNCTION("""COMPUTED_VALUE"""),"0.05% / 0.05%") | I26: =IFERROR(__xludf.DUMMYFUNCTION("""COMPUTED_VALUE"""),34.0) | J26: =IFERROR(__xludf.DUMMYFUNCTION("""COMPUTED_VALUE"""),170.0) | K26: =IFERROR(__xludf.DUMMYFUNCTION("""COMPUTED_VALUE"""),340.0) | L26: =IFERROR(__xludf.DUMMYFUNCTION("""COMPUTED_VALUE"""),850.0) | M26: =IFERROR(__xludf.DUMMYFUNCTION("""COMPUTED_VALUE"""),1700.0) | N26: =IFERROR(__xludf.DUMMYFUNCTION("""COMPUTED_VALUE"""),"Passive") | O26: =IFERROR(__xludf.DUMMYFUNCTION("""COMPUTED_VALUE"""),"CFS") | P26: =IFERROR(__xludf.DUMMYFUNCTION("""COMPUTED_VALUE"""),45068.0) | Q26: =IFERROR(__xludf.DUMMYFUNCTION("""COMPUTED_VALUE"""),"Option from Colonial First State Index Series. Portfolio rebates for balances above $100,000. Read the link for more info.")
B27: =IFERROR(__xludf.DUMMYFUNCTION("""COMPUTED_VALUE"""),"Vanguard Super") | C27: =IFERROR(__xludf.DUMMYFUNCTION("""COMPUTED_VALUE"""),"Retail") | D27: =IFERROR(__xludf.DUMMYFUNCTION("""COMPUTED_VALUE"""),0.0) | E27: =IFERROR(__xludf.DUMMYFUNCTION("""COMPUTED_VALUE"""),0.0035) | F27: =IFERROR(__xludf.DUMMYFUNCTION("""COMPUTED_VALUE"""),"NA") | G27: =IFERROR(__xludf.DUMMYFUNCTION("""COMPUTED_VALUE"""),0.0021) | H27: =IFERROR(__xludf.DUMMYFUNCTION("""COMPUTED_VALUE"""),"0.09% / 0.09%") | I27: =IFERROR(__xludf.DUMMYFUNCTION("""COMPUTED_VALUE"""),56.0) | J27: =IFERROR(__xludf.DUMMYFUNCTION("""COMPUTED_VALUE"""),280.0) | K27: =IFERROR(__xludf.DUMMYFUNCTION("""COMPUTED_VALUE"""),560.0) | L27: =IFERROR(__xludf.DUMMYFUNCTION("""COMPUTED_VALUE"""),1400.0) | M27: =IFERROR(__xludf.DUMMYFUNCTION("""COMPUTED_VALUE"""),2800.0) | N27: =IFERROR(__xludf.DUMMYFUNCTION("""COMPUTED_VALUE"""),"Passive") | O27: =IFERROR(__xludf.DUMMYFUNCTION("""COMPUTED_VALUE"""),"Vanguard Super") | P27: =IFERROR(__xludf.DUMMYFUNCTION("""COMPUTED_VALUE"""),44837.0) | Q27: =IFERROR(__xludf.DUMMYFUNCTION("""COMPUTED_VALUE"""),"A balance above $850,000 will have an admin fee of 0.05% instead.")
B28: =IFERROR(__xludf.DUMMYFUNCTION("""COMPUTED_VALUE"""),"Virgin Money") | C28: =IFERROR(__xludf.DUMMYFUNCTION("""COMPUTED_VALUE"""),"Retail") | D28: =IFERROR(__xludf.DUMMYFUNCTION("""COMPUTED_VALUE"""),58.0) | E28: =IFERROR(__xludf.DUMMYFUNCTION("""COMPUTED_VALUE"""),0.00411) | F28: =IFERROR(__xludf.DUMMYFUNCTION("""COMPUTED_VALUE"""),"NA") | G28: =IFERROR(__xludf.DUMMYFUNCTION("""COMPUTED_VALUE"""),0.0029) | H28: =IFERROR(__xludf.DUMMYFUNCTION("""COMPUTED_VALUE"""),"Nil") | I28: =IFERROR(__xludf.DUMMYFUNCTION("""COMPUTED_VALUE"""),128.1) | J28: =IFERROR(__xludf.DUMMYFUNCTION("""COMPUTED_VALUE"""),408.5) | K28: =IFERROR(__xludf.DUMMYFUNCTION("""COMPUTED_VALUE"""),759.0) | L28: =IFERROR(__xludf.DUMMYFUNCTION("""COMPUTED_VALUE"""),1810.5) | M28: =IFERROR(__xludf.DUMMYFUNCTION("""COMPUTED_VALUE"""),3563.0) | N28: =IFERROR(__xludf.DUMMYFUNCTION("""COMPUTED_VALUE"""),"Passive") | O28: =IFERROR(__xludf.DUMMYFUNCTION("""COMPUTED_VALUE"""),"Virgin Money") | P28: =IFERROR(__xludf.DUMMYFUNCTION("""COMPUTED_VALUE"""),45107.0)
B29: =IFERROR(__xludf.DUMMYFUNCTION("""COMPUTED_VALUE"""),"Spaceship") | C29: =IFERROR(__xludf.DUMMYFUNCTION("""COMPUTED_VALUE"""),"Retail") | D29: =IFERROR(__xludf.DUMMYFUNCTION("""COMPUTED_VALUE"""),78.0) | E29: =IFERROR(__xludf.DUMMYFUNCTION("""COMPUTED_VALUE"""),0.016849999999999997) | F29: =IFERROR(__xludf.DUMMYFUNCTION("""COMPUTED_VALUE"""),"NA") | G29: =IFERROR(__xludf.DUMMYFUNCTION("""COMPUTED_VALUE"""),0.00196) | H29: =IFERROR(__xludf.DUMMYFUNCTION("""COMPUTED_VALUE"""),"0.188% / 0.189%") | I29: =IFERROR(__xludf.DUMMYFUNCTION("""COMPUTED_VALUE"""),266.09999999999997) | J29: =IFERROR(__xludf.DUMMYFUNCTION("""COMPUTED_VALUE"""),1018.4999999999999) | K29: =IFERROR(__xludf.DUMMYFUNCTION("""COMPUTED_VALUE"""),1958.9999999999998) | L29: =IFERROR(__xludf.DUMMYFUNCTION("""COMPUTED_VALUE"""),4780.499999999999) | M29: =IFERROR(__xludf.DUMMYFUNCTION("""COMPUTED_VALUE"""),9482.999999999998) | N29: =IFERROR(__xludf.DUMMYFUNCTION("""COMPUTED_VALUE"""),"Active") | O29: =IFERROR(__xludf.DUMMYFUNCTION("""COMPUTED_VALUE"""),"Spaceship") | P29: =IFERROR(__xludf.DUMMYFUNCTION("""COMPUTED_VALUE"""),44834.0) | Q29: =IFERROR(__xludf.DUMMYFUNCTION("""COMPUTED_VALUE"""),"GrowthX option. No $78 admin fee for balances <$6,000")
B30: =IFERROR(__xludf.DUMMYFUNCTION("""COMPUTED_VALUE"""),"Spaceship") | C30: =IFERROR(__xludf.DUMMYFUNCTION("""COMPUTED_VALUE"""),"Retail") | D30: =IFERROR(__xludf.DUMMYFUNCTION("""COMPUTED_VALUE"""),78.0) | E30: =IFERROR(__xludf.DUMMYFUNCTION("""COMPUTED_VALUE"""),0.01542) | F30: =IFERROR(__xludf.DUMMYFUNCTION("""COMPUTED_VALUE"""),"NA") | G30: =IFERROR(__xludf.DUMMYFUNCTION("""COMPUTED_VALUE"""),0.0) | H30: =IFERROR(__xludf.DUMMYFUNCTION("""COMPUTED_VALUE"""),"0.08% / 0.08%") | I30: =IFERROR(__xludf.DUMMYFUNCTION("""COMPUTED_VALUE"""),232.2) | J30: =IFERROR(__xludf.DUMMYFUNCTION("""COMPUTED_VALUE"""),849.0) | K30: =IFERROR(__xludf.DUMMYFUNCTION("""COMPUTED_VALUE"""),1620.0) | L30: =IFERROR(__xludf.DUMMYFUNCTION("""COMPUTED_VALUE"""),3933.0) | M30: =IFERROR(__xludf.DUMMYFUNCTION("""COMPUTED_VALUE"""),7788.0) | N30: =IFERROR(__xludf.DUMMYFUNCTION("""COMPUTED_VALUE"""),"Passive") | O30: =IFERROR(__xludf.DUMMYFUNCTION("""COMPUTED_VALUE"""),"Spaceship") | P30: =IFERROR(__xludf.DUMMYFUNCTION("""COMPUTED_VALUE"""),44834.0) | Q30: =IFERROR(__xludf.DUMMYFUNCTION("""COMPUTED_VALUE"""),"Global Index option. No $78 admin fee for balances <$6,000")
B31: =IFERROR(__xludf.DUMMYFUNCTION("""COMPUTED_VALUE"""),"AMP") | C31: =IFERROR(__xludf.DUMMYFUNCTION("""COMPUTED_VALUE"""),"Retail") | D31: =IFERROR(__xludf.DUMMYFUNCTION("""COMPUTED_VALUE"""),78.0) | E31: =IFERROR(__xludf.DUMMYFUNCTION("""COMPUTED_VALUE"""),0.00234) | F31: =IFERROR(__xludf.DUMMYFUNCTION("""COMPUTED_VALUE"""),950.0) | G31: =IFERROR(__xludf.DUMMYFUNCTION("""COMPUTED_VALUE"""),0.0091) | H31: =IFERROR(__xludf.DUMMYFUNCTION("""COMPUTED_VALUE"""),"Nil") | I31: =IFERROR(__xludf.DUMMYFUNCTION("""COMPUTED_VALUE"""),192.4) | J31: =IFERROR(__xludf.DUMMYFUNCTION("""COMPUTED_VALUE"""),650.0) | K31: =IFERROR(__xludf.DUMMYFUNCTION("""COMPUTED_VALUE"""),1222.0) | L31: =IFERROR(__xludf.DUMMYFUNCTION("""COMPUTED_VALUE"""),2938.0) | M31: =IFERROR(__xludf.DUMMYFUNCTION("""COMPUTED_VALUE"""),5578.0) | N31: =IFERROR(__xludf.DUMMYFUNCTION("""COMPUTED_VALUE"""),"Active") | O31: =IFERROR(__xludf.DUMMYFUNCTION("""COMPUTED_VALUE"""),"AMP") | P31: =IFERROR(__xludf.DUMMYFUNCTION("""COMPUTED_VALUE"""),45108.0)
B32: =IFERROR(__xludf.DUMMYFUNCTION("""COMPUTED_VALUE"""),"AMP") | C32: =IFERROR(__xludf.DUMMYFUNCTION("""COMPUTED_VALUE"""),"Retail") | D32: =IFERROR(__xludf.DUMMYFUNCTION("""COMPUTED_VALUE"""),78.0) | E32: =IFERROR(__xludf.DUMMYFUNCTION("""COMPUTED_VALUE"""),0.00234) | F32: =IFERROR(__xludf.DUMMYFUNCTION("""COMPUTED_VALUE"""),950.0) | G32: =IFERROR(__xludf.DUMMYFUNCTION("""COMPUTED_VALUE"""),0.0027) | H32: =IFERROR(__xludf.DUMMYFUNCTION("""COMPUTED_VALUE"""),"Nil") | I32: =IFERROR(__xludf.DUMMYFUNCTION("""COMPUTED_VALUE"""),128.4) | J32: =IFERROR(__xludf.DUMMYFUNCTION("""COMPUTED_VALUE"""),330.0) | K32: =IFERROR(__xludf.DUMMYFUNCTION("""COMPUTED_VALUE"""),582.0) | L32: =IFERROR(__xludf.DUMMYFUNCTION("""COMPUTED_VALUE"""),1338.0) | M32: =IFERROR(__xludf.DUMMYFUNCTION("""COMPUTED_VALUE"""),2378.0) | N32: =IFERROR(__xludf.DUMMYFUNCTION("""COMPUTED_VALUE"""),"Passive") | O32: =IFERROR(__xludf.DUMMYFUNCTION("""COMPUTED_VALUE"""),"AMP") | P32: =IFERROR(__xludf.DUMMYFUNCTION("""COMPUTED_VALUE"""),45108.0)
B33: =IFERROR(__xludf.DUMMYFUNCTION("""COMPUTED_VALUE"""),"ANZ") | C33: =IFERROR(__xludf.DUMMYFUNCTION("""COMPUTED_VALUE"""),"Retail") | D33: =IFERROR(__xludf.DUMMYFUNCTION("""COMPUTED_VALUE"""),60.0) | E33: =IFERROR(__xludf.DUMMYFUNCTION("""COMPUTED_VALUE"""),0.0021) | F33: =IFERROR(__xludf.DUMMYFUNCTION("""COMPUTED_VALUE"""),"NA") | G33: =IFERROR(__xludf.DUMMYFUNCTION("""COMPUTED_VALUE"""),0.004) | H33: =IFERROR(__xludf.DUMMYFUNCTION("""COMPUTED_VALUE"""),"Nil") | I33: =IFERROR(__xludf.DUMMYFUNCTION("""COMPUTED_VALUE"""),121.0) | J33: =IFERROR(__xludf.DUMMYFUNCTION("""COMPUTED_VALUE"""),365.0) | K33: =IFERROR(__xludf.DUMMYFUNCTION("""COMPUTED_VALUE"""),670.0) | L33: =IFERROR(__xludf.DUMMYFUNCTION("""COMPUTED_VALUE"""),1585.0) | M33: =IFERROR(__xludf.DUMMYFUNCTION("""COMPUTED_VALUE"""),3110.0) | N33: =IFERROR(__xludf.DUMMYFUNCTION("""COMPUTED_VALUE"""),"Active") | O33: =IFERROR(__xludf.DUMMYFUNCTION("""COMPUTED_VALUE"""),"ANZ") | P33: =IFERROR(__xludf.DUMMYFUNCTION("""COMPUTED_VALUE"""),44895.0)
B34: =IFERROR(__xludf.DUMMYFUNCTION("""COMPUTED_VALUE"""),"Mercer") | C34: =IFERROR(__xludf.DUMMYFUNCTION("""COMPUTED_VALUE"""),"Retail") | D34: =IFERROR(__xludf.DUMMYFUNCTION("""COMPUTED_VALUE"""),0.0) | E34: =IFERROR(__xludf.DUMMYFUNCTION("""COMPUTED_VALUE"""),0.00167) | F34: =IFERROR(__xludf.DUMMYFUNCTION("""COMPUTED_VALUE"""),835.0) | G34: =IFERROR(__xludf.DUMMYFUNCTION("""COMPUTED_VALUE"""),0.0063) | H34: =IFERROR(__xludf.DUMMYFUNCTION("""COMPUTED_VALUE"""),"Nil") | I34: =IFERROR(__xludf.DUMMYFUNCTION("""COMPUTED_VALUE"""),79.7) | J34: =IFERROR(__xludf.DUMMYFUNCTION("""COMPUTED_VALUE"""),398.5) | K34: =IFERROR(__xludf.DUMMYFUNCTION("""COMPUTED_VALUE"""),797.0) | L34: =IFERROR(__xludf.DUMMYFUNCTION("""COMPUTED_VALUE"""),1992.5) | M34: =IFERROR(__xludf.DUMMYFUNCTION("""COMPUTED_VALUE"""),3985.0) | N34: =IFERROR(__xludf.DUMMYFUNCTION("""COMPUTED_VALUE"""),"Active") | O34: =IFERROR(__xludf.DUMMYFUNCTION("""COMPUTED_VALUE"""),"Mercer") | P34: =IFERROR(__xludf.DUMMYFUNCTION("""COMPUTED_VALUE"""),45076.0) | Q34: =IFERROR(__xludf.DUMMYFUNCTION("""COMPUTED_VALUE"""),"Mercer Diversified Shares option")
B35: =IFERROR(__xludf.DUMMYFUNCTION("""COMPUTED_VALUE"""),"Mercer") | C35: =IFERROR(__xludf.DUMMYFUNCTION("""COMPUTED_VALUE"""),"Retail") | D35: =IFERROR(__xludf.DUMMYFUNCTION("""COMPUTED_VALUE"""),0.0) | E35: =IFERROR(__xludf.DUMMYFUNCTION("""COMPUTED_VALUE"""),0.00167) | F35: =IFERROR(__xludf.DUMMYFUNCTION("""COMPUTED_VALUE"""),835.0) | G35: =IFERROR(__xludf.DUMMYFUNCTION("""COMPUTED_VALUE"""),0.0028) | H35: =IFERROR(__xludf.DUMMYFUNCTION("""COMPUTED_VALUE"""),"Nil") | I35: =IFERROR(__xludf.DUMMYFUNCTION("""COMPUTED_VALUE"""),44.7) | J35: =IFERROR(__xludf.DUMMYFUNCTION("""COMPUTED_VALUE"""),223.5) | K35: =IFERROR(__xludf.DUMMYFUNCTION("""COMPUTED_VALUE"""),447.0) | L35: =IFERROR(__xludf.DUMMYFUNCTION("""COMPUTED_VALUE"""),1117.5) | M35: =IFERROR(__xludf.DUMMYFUNCTION("""COMPUTED_VALUE"""),2235.0) | N35: =IFERROR(__xludf.DUMMYFUNCTION("""COMPUTED_VALUE"""),"Passive") | O35: =IFERROR(__xludf.DUMMYFUNCTION("""COMPUTED_VALUE"""),"Mercer") | P35: =IFERROR(__xludf.DUMMYFUNCTION("""COMPUTED_VALUE"""),45076.0) | Q35: =IFERROR(__xludf.DUMMYFUNCTION("""COMPUTED_VALUE"""),"Mercer Enhanced Passive High Growth option")
B36: =IFERROR(__xludf.DUMMYFUNCTION("""COMPUTED_VALUE"""),"MLC") | C36: =IFERROR(__xludf.DUMMYFUNCTION("""COMPUTED_VALUE"""),"Retail") | D36: =IFERROR(__xludf.DUMMYFUNCTION("""COMPUTED_VALUE"""),78.0) | E36: =IFERROR(__xludf.DUMMYFUNCTION("""COMPUTED_VALUE"""),0.0032) | F36: =IFERROR(__xludf.DUMMYFUNCTION("""COMPUTED_VALUE"""),2500.0) | G36: =IFERROR(__xludf.DUMMYFUNCTION("""COMPUTED_VALUE"""),0.0146) | H36: =IFERROR(__xludf.DUMMYFUNCTION("""COMPUTED_VALUE"""),"0.15% / 0.15%") | I36: =IFERROR(__xludf.DUMMYFUNCTION("""COMPUTED_VALUE"""),256.0) | J36: =IFERROR(__xludf.DUMMYFUNCTION("""COMPUTED_VALUE"""),968.0) | K36: =IFERROR(__xludf.DUMMYFUNCTION("""COMPUTED_VALUE"""),1858.0) | L36: =IFERROR(__xludf.DUMMYFUNCTION("""COMPUTED_VALUE"""),4528.0) | M36: =IFERROR(__xludf.DUMMYFUNCTION("""COMPUTED_VALUE"""),8978.0) | N36: =IFERROR(__xludf.DUMMYFUNCTION("""COMPUTED_VALUE"""),"Active") | O36: =IFERROR(__xludf.DUMMYFUNCTION("""COMPUTED_VALUE"""),"MLC") | P36: =IFERROR(__xludf.DUMMYFUNCTION("""COMPUTED_VALUE"""),45072.0) | Q36: =IFERROR(__xludf.DUMMYFUNCTION("""COMPUTED_VALUE"""),"Admin fee capped at $2,500 (excludes 0.02% levy fee). Percentage admin fee is 0.10% for remaining balance over $150,000. Fixed fee is deducted monthly if your account balance is below $50,000 when the percentage administration fee is deducted.")
B37: =IFERROR(__xludf.DUMMYFUNCTION("""COMPUTED_VALUE"""),"MLC") | C37: =IFERROR(__xludf.DUMMYFUNCTION("""COMPUTED_VALUE"""),"Retail") | D37: =IFERROR(__xludf.DUMMYFUNCTION("""COMPUTED_VALUE"""),78.0) | E37: =IFERROR(__xludf.DUMMYFUNCTION("""COMPUTED_VALUE"""),0.0032) | F37: =IFERROR(__xludf.DUMMYFUNCTION("""COMPUTED_VALUE"""),2500.0) | G37: =IFERROR(__xludf.DUMMYFUNCTION("""COMPUTED_VALUE"""),0.0029) | H37: =IFERROR(__xludf.DUMMYFUNCTION("""COMPUTED_VALUE"""),"0.10% / 0.10%") | I37: =IFERROR(__xludf.DUMMYFUNCTION("""COMPUTED_VALUE"""),139.0) | J37: =IFERROR(__xludf.DUMMYFUNCTION("""COMPUTED_VALUE"""),383.0) | K37: =IFERROR(__xludf.DUMMYFUNCTION("""COMPUTED_VALUE"""),688.0) | L37: =IFERROR(__xludf.DUMMYFUNCTION("""COMPUTED_VALUE"""),1603.0) | M37: =IFERROR(__xludf.DUMMYFUNCTION("""COMPUTED_VALUE"""),3128.0) | N37: =IFERROR(__xludf.DUMMYFUNCTION("""COMPUTED_VALUE"""),"Passive") | O37: =IFERROR(__xludf.DUMMYFUNCTION("""COMPUTED_VALUE"""),"MLC") | P37: =IFERROR(__xludf.DUMMYFUNCTION("""COMPUTED_VALUE"""),45072.0) | Q37: =IFERROR(__xludf.DUMMYFUNCTION("""COMPUTED_VALUE"""),"Admin fee capped at $2,500 (excludes 0.02% levy fee). Percentage admin fee is 0.10% for remaining balance over $150,000. Fixed fee is deducted monthly if your account balance is below $50,000 when the percentage administration fee is deducted.")
B38: =IFERROR(__xludf.DUMMYFUNCTION("""COMPUTED_VALUE"""),"TelstraSuper") | C38: =IFERROR(__xludf.DUMMYFUNCTION("""COMPUTED_VALUE"""),"Corporate ") | D38: =IFERROR(__xludf.DUMMYFUNCTION("""COMPUTED_VALUE"""),52.0) | E38: =IFERROR(__xludf.DUMMYFUNCTION("""COMPUTED_VALUE"""),0.0017) | F38: =IFERROR(__xludf.DUMMYFUNCTION("""COMPUTED_VALUE"""),1700.0) | G38: =IFERROR(__xludf.DUMMYFUNCTION("""COMPUTED_VALUE"""),0.0086) | H38: =IFERROR(__xludf.DUMMYFUNCTION("""COMPUTED_VALUE"""),"Nil") | I38: =IFERROR(__xludf.DUMMYFUNCTION("""COMPUTED_VALUE"""),155.0) | J38: =IFERROR(__xludf.DUMMYFUNCTION("""COMPUTED_VALUE"""),567.0) | K38: =IFERROR(__xludf.DUMMYFUNCTION("""COMPUTED_VALUE"""),1082.0) | L38: =IFERROR(__xludf.DUMMYFUNCTION("""COMPUTED_VALUE"""),2627.0) | M38: =IFERROR(__xludf.DUMMYFUNCTION("""COMPUTED_VALUE"""),5202.0) | N38: =IFERROR(__xludf.DUMMYFUNCTION("""COMPUTED_VALUE"""),"Active") | O38: =IFERROR(__xludf.DUMMYFUNCTION("""COMPUTED_VALUE"""),"TelstraSuper") | P38: =IFERROR(__xludf.DUMMYFUNCTION("""COMPUTED_VALUE"""),45117.0) | Q38: =IFERROR(__xludf.DUMMYFUNCTION("""COMPUTED_VALUE"""),"ESG Integration")
B39: =IFERROR(__xludf.DUMMYFUNCTION("""COMPUTED_VALUE"""),"PSSap") | C39: =IFERROR(__xludf.DUMMYFUNCTION("""COMPUTED_VALUE"""),"Public sector") | D39: =IFERROR(__xludf.DUMMYFUNCTION("""COMPUTED_VALUE"""),84.0) | E39: =IFERROR(__xludf.DUMMYFUNCTION("""COMPUTED_VALUE"""),0.0) | F39: =IFERROR(__xludf.DUMMYFUNCTION("""COMPUTED_VALUE"""),"NA") | G39: =IFERROR(__xludf.DUMMYFUNCTION("""COMPUTED_VALUE"""),0.009) | H39: =IFERROR(__xludf.DUMMYFUNCTION("""COMPUTED_VALUE"""),"0.15% / 0.14%") | I39: =IFERROR(__xludf.DUMMYFUNCTION("""COMPUTED_VALUE"""),174.0) | J39: =IFERROR(__xludf.DUMMYFUNCTION("""COMPUTED_VALUE"""),534.0) | K39: =IFERROR(__xludf.DUMMYFUNCTION("""COMPUTED_VALUE"""),983.9999999999999) | L39: =IFERROR(__xludf.DUMMYFUNCTION("""COMPUTED_VALUE"""),2334.0) | M39: =IFERROR(__xludf.DUMMYFUNCTION("""COMPUTED_VALUE"""),4584.0) | N39: =IFERROR(__xludf.DUMMYFUNCTION("""COMPUTED_VALUE"""),"Active") | O39: =IFERROR(__xludf.DUMMYFUNCTION("""COMPUTED_VALUE"""),"PSSap") | P39: =IFERROR(__xludf.DUMMYFUNCTION("""COMPUTED_VALUE"""),44986.0)
B41: =IFERROR(__xludf.DUMMYFUNCTION("IMPORTRANGE(""https://docs.google.com/spreadsheets/d/1A2a_CIOEK-POlkK616JVZN4ouhsUMkdiZXm1KiJuqJQ/edit#gid=814241220"",""Performance!A1:E300"")"),"Performance ending 30 June 2023")
B42: =IFERROR(__xludf.DUMMYFUNCTION("""COMPUTED_VALUE"""),"Select Australian allocation:") | C42: =IFERROR(__xludf.DUMMYFUNCTION("""COMPUTED_VALUE"""),0.4)
B43: =IFERROR(__xludf.DUMMYFUNCTION("""COMPUTED_VALUE"""),"Past performance does not indicate future results.")
B44: =IFERROR(__xludf.DUMMYFUNCTION("""COMPUTED_VALUE"""),"Super fund") | D44: =IFERROR(__xludf.DUMMYFUNCTION("""COMPUTED_VALUE"""),"Performance")
B45: =IFERROR(__xludf.DUMMYFUNCTION("""COMPUTED_VALUE"""),"Name") | C45: =IFERROR(__xludf.DUMMYFUNCTION("""COMPUTED_VALUE"""),"Option") | D45: =IFERROR(__xludf.DUMMYFUNCTION("""COMPUTED_VALUE"""),"1 year") | E45: =IFERROR(__xludf.DUMMYFUNCTION("""COMPUTED_VALUE"""),"3 years") | F45: =IFERROR(__xludf.DUMMYFUNCTION("""COMPUTED_VALUE"""),"5 years") | G45: Avg 1 | H45: avg 3 | I45: avg 5
B46: =IFERROR(__xludf.DUMMYFUNCTION("""COMPUTED_VALUE"""),"Aware Super") | C46: =IFERROR(__xludf.DUMMYFUNCTION("""COMPUTED_VALUE"""),"Aus shares") | D46: =IFERROR(__xludf.DUMMYFUNCTION("""COMPUTED_VALUE"""),0.1357) | E46: =IFERROR(__xludf.DUMMYFUNCTION("""COMPUTED_VALUE"""),0.1122) | F46: =IFERROR(__xludf.DUMMYFUNCTION("""COMPUTED_VALUE"""),0.0775) | G46: =IFERROR(AVERAGEIF($B$46:$B$158, B46, $D$46:$D$158), "") | H46: =IFERROR(AVERAGEIF($B$46:$B$158, B46, $E$46:$E$158), "") | I46: =IFERROR(AVERAGEIF($B$46:$B$158, B46, $F$46:$F$158), "")
B47: =IFERROR(__xludf.DUMMYFUNCTION("""COMPUTED_VALUE"""),"Aware Super") | C47: =IFERROR(__xludf.DUMMYFUNCTION("""COMPUTED_VALUE"""),"Int shares") | D47: =IFERROR(__xludf.DUMMYFUNCTION("""COMPUTED_VALUE"""),0.2072) | E47: =IFERROR(__xludf.DUMMYFUNCTION("""COMPUTED_VALUE"""),0.1211) | F47: =IFERROR(__xludf.DUMMYFUNCTION("""COMPUTED_VALUE"""),0.1063) | G47: =IFERROR(AVERAGEIF($B$46:$B$158, B47, $D$46:$D$158), "") | H47: =IFERROR(AVERAGEIF($B$46:$B$158, B47, $E$46:$E$158), "") | I47: =IFERROR(AVERAGEIF($B$46:$B$158, B47, $F$46:$F$158), "")
B48: =IFERROR(__xludf.DUMMYFUNCTION("""COMPUTED_VALUE"""),"Aware Super") | C48: =IFERROR(__xludf.DUMMYFUNCTION("""COMPUTED_VALUE"""),"Aus & Int shares") | D48: =IFERROR(__xludf.DUMMYFUNCTION("""COMPUTED_VALUE"""),0.17859999999999998) | E48: =IFERROR(__xludf.DUMMYFUNCTION("""COMPUTED_VALUE"""),0.11754) | F48: =IFERROR(__xludf.DUMMYFUNCTION("""COMPUTED_VALUE"""),0.09478) | G48: =IFERROR(AVERAGEIF($B$46:$B$158, B48, $D$46:$D$158), "") | H48: =IFERROR(AVERAGEIF($B$46:$B$158, B48, $E$46:$E$158), "") | I48: =IFERROR(AVERAGEIF($B$46:$B$158, B48, $F$46:$F$158), "")
B49: =IFERROR(__xludf.DUMMYFUNCTION("""COMPUTED_VALUE"""),"Aware Super") | C49: =IFERROR(__xludf.DUMMYFUNCTION("""COMPUTED_VALUE"""),"High Growth") | D49: =IFERROR(__xludf.DUMMYFUNCTION("""COMPUTED_VALUE"""),0.1072) | E49: =IFERROR(__xludf.DUMMYFUNCTION("""COMPUTED_VALUE"""),0.0956) | F49: =IFERROR(__xludf.DUMMYFUNCTION("""COMPUTED_VALUE"""),0.0764) | G49: =IFERROR(AVERAGEIF($B$46:$B$158, B49, $D$46:$D$158), "") | H49: =IFERROR(AVERAGEIF($B$46:$B$158, B49, $E$46:$E$158), "") | I49: =IFERROR(AVERAGEIF($B$46:$B$158, B49, $F$46:$F$158), "")
B50: =IFERROR(__xludf.DUMMYFUNCTION("""COMPUTED_VALUE"""),"ART") | C50: =IFERROR(__xludf.DUMMYFUNCTION("""COMPUTED_VALUE"""),"Aus shares") | D50: =IFERROR(__xludf.DUMMYFUNCTION("""COMPUTED_VALUE"""),0.1407) | E50: =IFERROR(__xludf.DUMMYFUNCTION("""COMPUTED_VALUE"""),0.116) | F50: =IFERROR(__xludf.DUMMYFUNCTION("""COMPUTED_VALUE"""),0.0709) | G50: =IFERROR(AVERAGEIF($B$46:$B$158, B50, $D$46:$D$158), "") | H50: =IFERROR(AVERAGEIF($B$46:$B$158, B50, $E$46:$E$158), "") | I50: =IFERROR(AVERAGEIF($B$46:$B$158, B50, $F$46:$F$158), "")
B51: =IFERROR(__xludf.DUMMYFUNCTION("""COMPUTED_VALUE"""),"ART") | C51: =IFERROR(__xludf.DUMMYFUNCTION("""COMPUTED_VALUE"""),"Aus shares") | D51: =IFERROR(__xludf.DUMMYFUNCTION("""COMPUTED_VALUE"""),0.1424) | E51: =IFERROR(__xludf.DUMMYFUNCTION("""COMPUTED_VALUE"""),0.1123) | F51: =IFERROR(__xludf.DUMMYFUNCTION("""COMPUTED_VALUE"""),0.0768) | G51: =IFERROR(AVERAGEIF($B$46:$B$158, B51, $D$46:$D$158), "") | H51: =IFERROR(AVERAGEIF($B$46:$B$158, B51, $E$46:$E$158), "") | I51: =IFERROR(AVERAGEIF($B$46:$B$158, B51, $F$46:$F$158), "")
B52: =IFERROR(__xludf.DUMMYFUNCTION("""COMPUTED_VALUE"""),"ART") | C52: =IFERROR(__xludf.DUMMYFUNCTION("""COMPUTED_VALUE"""),"Int shares") | D52: =IFERROR(__xludf.DUMMYFUNCTION("""COMPUTED_VALUE"""),0.2037) | E52: =IFERROR(__xludf.DUMMYFUNCTION("""COMPUTED_VALUE"""),0.1238) | F52: =IFERROR(__xludf.DUMMYFUNCTION("""COMPUTED_VALUE"""),0.1013) | G52: =IFERROR(AVERAGEIF($B$46:$B$158, B52, $D$46:$D$158), "") | H52: =IFERROR(AVERAGEIF($B$46:$B$158, B52, $E$46:$E$158), "") | I52: =IFERROR(AVERAGEIF($B$46:$B$158, B52, $F$46:$F$158), "")
B53: =IFERROR(__xludf.DUMMYFUNCTION("""COMPUTED_VALUE"""),"ART") | C53: =IFERROR(__xludf.DUMMYFUNCTION("""COMPUTED_VALUE"""),"Aus & Int shares") | D53: =IFERROR(__xludf.DUMMYFUNCTION("""COMPUTED_VALUE"""),0.17918) | E53: =IFERROR(__xludf.DUMMYFUNCTION("""COMPUTED_VALUE"""),0.1192) | F53: =IFERROR(__xludf.DUMMYFUNCTION("""COMPUTED_VALUE"""),0.0915) | G53: =IFERROR(AVERAGEIF($B$46:$B$158, B53, $D$46:$D$158), "") | H53: =IFERROR(AVERAGEIF($B$46:$B$158, B53, $E$46:$E$158), "") | I53: =IFERROR(AVERAGEIF($B$46:$B$158, B53, $F$46:$F$158), "")
B54: =IFERROR(__xludf.DUMMYFUNCTION("""COMPUTED_VALUE"""),"ART") | C54: =IFERROR(__xludf.DUMMYFUNCTION("""COMPUTED_VALUE"""),"High Growth") | D54: =IFERROR(__xludf.DUMMYFUNCTION("""COMPUTED_VALUE"""),0.1196) | E54: =IFERROR(__xludf.DUMMYFUNCTION("""COMPUTED_VALUE"""),0.1195) | F54: =IFERROR(__xludf.DUMMYFUNCTION("""COMPUTED_VALUE"""),0.0836) | G54: =IFERROR(AVERAGEIF($B$46:$B$158, B54, $D$46:$D$158), "") | H54: =IFERROR(AVERAGEIF($B$46:$B$158, B54, $E$46:$E$158), "") | I54: =IFERROR(AVERAGEIF($B$46:$B$158, B54, $F$46:$F$158), "")
B55: =IFERROR(__xludf.DUMMYFUNCTION("""COMPUTED_VALUE"""),"Qsuper") | C55: =IFERROR(__xludf.DUMMYFUNCTION("""COMPUTED_VALUE"""),"Aus shares") | D55: =IFERROR(__xludf.DUMMYFUNCTION("""COMPUTED_VALUE"""),0.0999) | E55: =IFERROR(__xludf.DUMMYFUNCTION("""COMPUTED_VALUE"""),0.1031) | F55: =IFERROR(__xludf.DUMMYFUNCTION("""COMPUTED_VALUE"""),0.0684) | G55: =IFERROR(AVERAGEIF($B$46:$B$158, B55, $D$46:$D$158), "") | H55: =IFERROR(AVERAGEIF($B$46:$B$158, B55, $E$46:$E$158), "") | I55: =IFERROR(AVERAGEIF($B$46:$B$158, B55, $F$46:$F$158), "")
B56: =IFERROR(__xludf.DUMMYFUNCTION("""COMPUTED_VALUE"""),"Qsuper") | C56: =IFERROR(__xludf.DUMMYFUNCTION("""COMPUTED_VALUE"""),"Int shares") | D56: =IFERROR(__xludf.DUMMYFUNCTION("""COMPUTED_VALUE"""),0.1188) | E56: =IFERROR(__xludf.DUMMYFUNCTION("""COMPUTED_VALUE"""),0.1081) | F56: =IFERROR(__xludf.DUMMYFUNCTION("""COMPUTED_VALUE"""),0.0783) | G56: =IFERROR(AVERAGEIF($B$46:$B$158, B56, $D$46:$D$158), "") | H56: =IFERROR(AVERAGEIF($B$46:$B$158, B56, $E$46:$E$158), "") | I56: =IFERROR(AVERAGEIF($B$46:$B$158, B56, $F$46:$F$158), "")
B57: =IFERROR(__xludf.DUMMYFUNCTION("""COMPUTED_VALUE"""),"Qsuper") | C57: =IFERROR(__xludf.DUMMYFUNCTION("""COMPUTED_VALUE"""),"Aus & Int shares") | D57: =IFERROR(__xludf.DUMMYFUNCTION("""COMPUTED_VALUE"""),0.11124) | E57: =IFERROR(__xludf.DUMMYFUNCTION("""COMPUTED_VALUE"""),0.1061) | F57: =IFERROR(__xludf.DUMMYFUNCTION("""COMPUTED_VALUE"""),0.07433999999999999) | G57: =IFERROR(AVERAGEIF($B$46:$B$158, B57, $D$46:$D$158), "") | H57: =IFERROR(AVERAGEIF($B$46:$B$158, B57, $E$46:$E$158), "") | I57: =IFERROR(AVERAGEIF($B$46:$B$158, B57, $F$46:$F$158), "")
B58: =IFERROR(__xludf.DUMMYFUNCTION("""COMPUTED_VALUE"""),"Qsuper") | C58: =IFERROR(__xludf.DUMMYFUNCTION("""COMPUTED_VALUE"""),"High Growth") | D58: =IFERROR(__xludf.DUMMYFUNCTION("""COMPUTED_VALUE"""),0.0453) | E58: =IFERROR(__xludf.DUMMYFUNCTION("""COMPUTED_VALUE"""),0.0611) | F58: =IFERROR(__xludf.DUMMYFUNCTION("""COMPUTED_VALUE"""),0.055) | G58: =IFERROR(AVERAGEIF($B$46:$B$158, B58, $D$46:$D$158), "") | H58: =IFERROR(AVERAGEIF($B$46:$B$158, B58, $E$46:$E$158), "") | I58: =IFERROR(AVERAGEIF($B$46:$B$158, B58, $F$46:$F$158), "")
B59: =IFERROR(__xludf.DUMMYFUNCTION("""COMPUTED_VALUE"""),"Hostplus") | C59: =IFERROR(__xludf.DUMMYFUNCTION("""COMPUTED_VALUE"""),"Aus shares") | D59: =IFERROR(__xludf.DUMMYFUNCTION("""COMPUTED_VALUE"""),0.1417) | E59: =IFERROR(__xludf.DUMMYFUNCTION("""COMPUTED_VALUE"""),0.123) | F59: =IFERROR(__xludf.DUMMYFUNCTION("""COMPUTED_VALUE"""),0.074) | G59: =IFERROR(AVERAGEIF($B$46:$B$158, B59, $D$46:$D$158), "") | H59: =IFERROR(AVERAGEIF($B$46:$B$158, B59, $E$46:$E$158), "") | I59: =IFERROR(AVERAGEIF($B$46:$B$158, B59, $F$46:$F$158), "")
B60: =IFERROR(__xludf.DUMMYFUNCTION("""COMPUTED_VALUE"""),"Hostplus") | C60: =IFERROR(__xludf.DUMMYFUNCTION("""COMPUTED_VALUE"""),"Aus shares") | D60: =IFERROR(__xludf.DUMMYFUNCTION("""COMPUTED_VALUE"""),0.1432) | G60: =IFERROR(AVERAGEIF($B$46:$B$158, B60, $D$46:$D$158), "") | H60: =IFERROR(AVERAGEIF($B$46:$B$158, B60, $E$46:$E$158), "") | I60: =IFERROR(AVERAGEIF($B$46:$B$158, B60, $F$46:$F$158), "")
B61: =IFERROR(__xludf.DUMMYFUNCTION("""COMPUTED_VALUE"""),"Hostplus") | C61: =IFERROR(__xludf.DUMMYFUNCTION("""COMPUTED_VALUE"""),"Int shares") | D61: =IFERROR(__xludf.DUMMYFUNCTION("""COMPUTED_VALUE"""),0.1516) | E61: =IFERROR(__xludf.DUMMYFUNCTION("""COMPUTED_VALUE"""),0.0794) | F61: =IFERROR(__xludf.DUMMYFUNCTION("""COMPUTED_VALUE"""),0.0728) | G61: =IFERROR(AVERAGEIF($B$46:$B$158, B61, $D$46:$D$158), "") | H61: =IFERROR(AVERAGEIF($B$46:$B$158, B61, $E$46:$E$158), "") | I61: =IFERROR(AVERAGEIF($B$46:$B$158, B61, $F$46:$F$158), "")
B62: =IFERROR(__xludf.DUMMYFUNCTION("""COMPUTED_VALUE"""),"Hostplus") | C62: =IFERROR(__xludf.DUMMYFUNCTION("""COMPUTED_VALUE"""),"Int shares") | D62: =IFERROR(__xludf.DUMMYFUNCTION("""COMPUTED_VALUE"""),0.2035) | E62: =IFERROR(__xludf.DUMMYFUNCTION("""COMPUTED_VALUE"""),0.123) | F62: =IFERROR(__xludf.DUMMYFUNCTION("""COMPUTED_VALUE"""),0.1045) | G62: =IFERROR(AVERAGEIF($B$46:$B$158, B62, $D$46:$D$158), "") | H62: =IFERROR(AVERAGEIF($B$46:$B$158, B62, $E$46:$E$158), "") | I62: =IFERROR(AVERAGEIF($B$46:$B$158, B62, $F$46:$F$158), "")
B63: =IFERROR(__xludf.DUMMYFUNCTION("""COMPUTED_VALUE"""),"Hostplus") | C63: =IFERROR(__xludf.DUMMYFUNCTION("""COMPUTED_VALUE"""),"Aus & Int shares") | D63: =IFERROR(__xludf.DUMMYFUNCTION("""COMPUTED_VALUE"""),0.14764) | E63: =IFERROR(__xludf.DUMMYFUNCTION("""COMPUTED_VALUE"""),0.09684) | F63: =IFERROR(__xludf.DUMMYFUNCTION("""COMPUTED_VALUE"""),0.07328000000000001) | G63: =IFERROR(AVERAGEIF($B$46:$B$158, B63, $D$46:$D$158), "") | H63: =IFERROR(AVERAGEIF($B$46:$B$158, B63, $E$46:$E$158), "") | I63: =IFERROR(AVERAGEIF($B$46:$B$158, B63, $F$46:$F$158), "")
B64: =IFERROR(__xludf.DUMMYFUNCTION("""COMPUTED_VALUE"""),"Hostplus") | C64: =IFERROR(__xludf.DUMMYFUNCTION("""COMPUTED_VALUE"""),"Aus & Int shares") | D64: =IFERROR(__xludf.DUMMYFUNCTION("""COMPUTED_VALUE"""),0.17937999999999998) | G64: =IFERROR(AVERAGEIF($B$46:$B$158, B64, $D$46:$D$158), "") | H64: =IFERROR(AVERAGEIF($B$46:$B$158, B64, $E$46:$E$158), "") | I64: =IFERROR(AVERAGEIF($B$46:$B$158, B64, $F$46:$F$158), "")
B65: =IFERROR(__xludf.DUMMYFUNCTION("""COMPUTED_VALUE"""),"Hostplus") | C65: =IFERROR(__xludf.DUMMYFUNCTION("""COMPUTED_VALUE"""),"High Growth") | D65: =IFERROR(__xludf.DUMMYFUNCTION("""COMPUTED_VALUE"""),0.1122) | E65: =IFERROR(__xludf.DUMMYFUNCTION("""COMPUTED_VALUE"""),0.1034) | F65: =IFERROR(__xludf.DUMMYFUNCTION("""COMPUTED_VALUE"""),0.0756) | G65: =IFERROR(AVERAGEIF($B$46:$B$158, B65, $D$46:$D$158), "") | H65: =IFERROR(AVERAGEIF($B$46:$B$158, B65, $E$46:$E$158), "") | I65: =IFERROR(AVERAGEIF($B$46:$B$158, B65, $F$46:$F$158), "")
B66: =IFERROR(__xludf.DUMMYFUNCTION("""COMPUTED_VALUE"""),"Rest") | C66: =IFERROR(__xludf.DUMMYFUNCTION("""COMPUTED_VALUE"""),"Aus shares") | D66: =IFERROR(__xludf.DUMMYFUNCTION("""COMPUTED_VALUE"""),0.148) | E66: =IFERROR(__xludf.DUMMYFUNCTION("""COMPUTED_VALUE"""),0.1174) | F66: =IFERROR(__xludf.DUMMYFUNCTION("""COMPUTED_VALUE"""),0.0676) | G66: =IFERROR(AVERAGEIF($B$46:$B$158, B66, $D$46:$D$158), "") | H66: =IFERROR(AVERAGEIF($B$46:$B$158, B66, $E$46:$E$158), "") | I66: =IFERROR(AVERAGEIF($B$46:$B$158, B66, $F$46:$F$158), "")
B67: =IFERROR(__xludf.DUMMYFUNCTION("""COMPUTED_VALUE"""),"Rest") | C67: =IFERROR(__xludf.DUMMYFUNCTION("""COMPUTED_VALUE"""),"Aus shares") | D67: =IFERROR(__xludf.DUMMYFUNCTION("""COMPUTED_VALUE"""),0.1455) | E67: =IFERROR(__xludf.DUMMYFUNCTION("""COMPUTED_VALUE"""),0.1084) | G67: =IFERROR(AVERAGEIF($B$46:$B$158, B67, $D$46:$D$158), "") | H67: =IFERROR(AVERAGEIF($B$46:$B$158, B67, $E$46:$E$158), "") | I67: =IFERROR(AVERAGEIF($B$46:$B$158, B67, $F$46:$F$158), "")
B68: =IFERROR(__xludf.DUMMYFUNCTION("""COMPUTED_VALUE"""),"Rest") | C68: =IFERROR(__xludf.DUMMYFUNCTION("""COMPUTED_VALUE"""),"Int shares") | D68: =IFERROR(__xludf.DUMMYFUNCTION("""COMPUTED_VALUE"""),0.192) | E68: =IFERROR(__xludf.DUMMYFUNCTION("""COMPUTED_VALUE"""),0.1136) | F68: =IFERROR(__xludf.DUMMYFUNCTION("""COMPUTED_VALUE"""),0.0815) | G68: =IFERROR(AVERAGEIF($B$46:$B$158, B68, $D$46:$D$158), "") | H68: =IFERROR(AVERAGEIF($B$46:$B$158, B68, $E$46:$E$158), "") | I68: =IFERROR(AVERAGEIF($B$46:$B$158, B68, $F$46:$F$158), "")
B69: =IFERROR(__xludf.DUMMYFUNCTION("""COMPUTED_VALUE"""),"Rest") | C69: =IFERROR(__xludf.DUMMYFUNCTION("""COMPUTED_VALUE"""),"Int shares") | D69: =IFERROR(__xludf.DUMMYFUNCTION("""COMPUTED_VALUE"""),0.2054) | E69: =IFERROR(__xludf.DUMMYFUNCTION("""COMPUTED_VALUE"""),0.1233) | G69: =IFERROR(AVERAGEIF($B$46:$B$158, B69, $D$46:$D$158), "") | H69: =IFERROR(AVERAGEIF($B$46:$B$158, B69, $E$46:$E$158), "") | I69: =IFERROR(AVERAGEIF($B$46:$B$158, B69, $F$46:$F$158), "")
B70: =IFERROR(__xludf.DUMMYFUNCTION("""COMPUTED_VALUE"""),"Rest") | C70: =IFERROR(__xludf.DUMMYFUNCTION("""COMPUTED_VALUE"""),"Aus & Int shares") | D70: =IFERROR(__xludf.DUMMYFUNCTION("""COMPUTED_VALUE"""),0.1744) | E70: =IFERROR(__xludf.DUMMYFUNCTION("""COMPUTED_VALUE"""),0.11512) | F70: =IFERROR(__xludf.DUMMYFUNCTION("""COMPUTED_VALUE"""),0.07594) | G70: =IFERROR(AVERAGEIF($B$46:$B$158, B70, $D$46:$D$158), "") | H70: =IFERROR(AVERAGEIF($B$46:$B$158, B70, $E$46:$E$158), "") | I70: =IFERROR(AVERAGEIF($B$46:$B$158, B70, $F$46:$F$158), "")
B71: =IFERROR(__xludf.DUMMYFUNCTION("""COMPUTED_VALUE"""),"Rest") | C71: =IFERROR(__xludf.DUMMYFUNCTION("""COMPUTED_VALUE"""),"Aus & Int shares") | D71: =IFERROR(__xludf.DUMMYFUNCTION("""COMPUTED_VALUE"""),0.18144) | E71: =IFERROR(__xludf.DUMMYFUNCTION("""COMPUTED_VALUE"""),0.11734) | G71: =IFERROR(AVERAGEIF($B$46:$B$158, B71, $D$46:$D$158), "") | H71: =IFERROR(AVERAGEIF($B$46:$B$158, B71, $E$46:$E$158), "") | I71: =IFERROR(AVERAGEIF($B$46:$B$158, B71, $F$46:$F$158), "")
B72: =IFERROR(__xludf.DUMMYFUNCTION("""COMPUTED_VALUE"""),"Rest") | C72: =IFERROR(__xludf.DUMMYFUNCTION("""COMPUTED_VALUE"""),"High Growth") | D72: =IFERROR(__xludf.DUMMYFUNCTION("""COMPUTED_VALUE"""),0.1207) | E72: =IFERROR(__xludf.DUMMYFUNCTION("""COMPUTED_VALUE"""),0.1056) | F72: =IFERROR(__xludf.DUMMYFUNCTION("""COMPUTED_VALUE"""),0.0723) | G72: =IFERROR(AVERAGEIF($B$46:$B$158, B72, $D$46:$D$158), "") | H72: =IFERROR(AVERAGEIF($B$46:$B$158, B72, $E$46:$E$158), "") | I72: =IFERROR(AVERAGEIF($B$46:$B$158, B72, $F$46:$F$158), "")
B73: =IFERROR(__xludf.DUMMYFUNCTION("""COMPUTED_VALUE"""),"Rest") | C73: =IFERROR(__xludf.DUMMYFUNCTION("""COMPUTED_VALUE"""),"SRI") | D73: =IFERROR(__xludf.DUMMYFUNCTION("""COMPUTED_VALUE"""),0.1168) | G73: =IFERROR(AVERAGEIF($B$46:$B$158, B73, $D$46:$D$158), "") | H73: =IFERROR(AVERAGEIF($B$46:$B$158, B73, $E$46:$E$158), "") | I73: =IFERROR(AVERAGEIF($B$46:$B$158, B73, $F$46:$F$158), "")
B74: =IFERROR(__xludf.DUMMYFUNCTION("""COMPUTED_VALUE"""),"Brighter Super") | C74: =IFERROR(__xludf.DUMMYFUNCTION("""COMPUTED_VALUE"""),"Aus shares") | D74: =IFERROR(__xludf.DUMMYFUNCTION("""COMPUTED_VALUE"""),0.1303) | E74: =IFERROR(__xludf.DUMMYFUNCTION("""COMPUTED_VALUE"""),0.1222) | F74: =IFERROR(__xludf.DUMMYFUNCTION("""COMPUTED_VALUE"""),0.0746) | G74: =IFERROR(AVERAGEIF($B$46:$B$158, B74, $D$46:$D$158), "") | H74: =IFERROR(AVERAGEIF($B$46:$B$158, B74, $E$46:$E$158), "") | I74: =IFERROR(AVERAGEIF($B$46:$B$158, B74, $F$46:$F$158), "")
B75: =IFERROR(__xludf.DUMMYFUNCTION("""COMPUTED_VALUE"""),"Brighter Super") | C75: =IFERROR(__xludf.DUMMYFUNCTION("""COMPUTED_VALUE"""),"Int shares") | D75: =IFERROR(__xludf.DUMMYFUNCTION("""COMPUTED_VALUE"""),0.1781) | E75: =IFERROR(__xludf.DUMMYFUNCTION("""COMPUTED_VALUE"""),0.108) | F75: =IFERROR(__xludf.DUMMYFUNCTION("""COMPUTED_VALUE"""),0.0868) | G75: =IFERROR(AVERAGEIF($B$46:$B$158, B75, $D$46:$D$158), "") | H75: =IFERROR(AVERAGEIF($B$46:$B$158, B75, $E$46:$E$158), "") | I75: =IFERROR(AVERAGEIF($B$46:$B$158, B75, $F$46:$F$158), "")
B76: =IFERROR(__xludf.DUMMYFUNCTION("""COMPUTED_VALUE"""),"Brighter Super") | C76: =IFERROR(__xludf.DUMMYFUNCTION("""COMPUTED_VALUE"""),"Aus & Int shares") | D76: =IFERROR(__xludf.DUMMYFUNCTION("""COMPUTED_VALUE"""),0.15898) | E76: =IFERROR(__xludf.DUMMYFUNCTION("""COMPUTED_VALUE"""),0.11368) | F76: =IFERROR(__xludf.DUMMYFUNCTION("""COMPUTED_VALUE"""),0.08192) | G76: =IFERROR(AVERAGEIF($B$46:$B$158, B76, $D$46:$D$158), "") | H76: =IFERROR(AVERAGEIF($B$46:$B$158, B76, $E$46:$E$158), "") | I76: =IFERROR(AVERAGEIF($B$46:$B$158, B76, $F$46:$F$158), "")
B77: =IFERROR(__xludf.DUMMYFUNCTION("""COMPUTED_VALUE"""),"Brighter Super") | C77: =IFERROR(__xludf.DUMMYFUNCTION("""COMPUTED_VALUE"""),"High Growth") | D77: =IFERROR(__xludf.DUMMYFUNCTION("""COMPUTED_VALUE"""),0.1261) | E77: =IFERROR(__xludf.DUMMYFUNCTION("""COMPUTED_VALUE"""),0.0932) | F77: =IFERROR(__xludf.DUMMYFUNCTION("""COMPUTED_VALUE"""),0.072) | G77: =IFERROR(AVERAGEIF($B$46:$B$158, B77, $D$46:$D$158), "") | H77: =IFERROR(AVERAGEIF($B$46:$B$158, B77, $E$46:$E$158), "") | I77: =IFERROR(AVERAGEIF($B$46:$B$158, B77, $F$46:$F$158), "")
B78: =IFERROR(__xludf.DUMMYFUNCTION("""COMPUTED_VALUE"""),"Australian Super") | C78: =IFERROR(__xludf.DUMMYFUNCTION("""COMPUTED_VALUE"""),"Aus shares") | D78: =IFERROR(__xludf.DUMMYFUNCTION("""COMPUTED_VALUE"""),0.1395) | E78: =IFERROR(__xludf.DUMMYFUNCTION("""COMPUTED_VALUE"""),0.1292) | F78: =IFERROR(__xludf.DUMMYFUNCTION("""COMPUTED_VALUE"""),0.0866) | G78: =IFERROR(AVERAGEIF($B$46:$B$158, B78, $D$46:$D$158), "") | H78: =IFERROR(AVERAGEIF($B$46:$B$158, B78, $E$46:$E$158), "") | I78: =IFERROR(AVERAGEIF($B$46:$B$158, B78, $F$46:$F$158), "")
B79: =IFERROR(__xludf.DUMMYFUNCTION("""COMPUTED_VALUE"""),"Australian Super") | C79: =IFERROR(__xludf.DUMMYFUNCTION("""COMPUTED_VALUE"""),"Int shares") | D79: =IFERROR(__xludf.DUMMYFUNCTION("""COMPUTED_VALUE"""),0.1745) | E79: =IFERROR(__xludf.DUMMYFUNCTION("""COMPUTED_VALUE"""),0.0951) | F79: =IFERROR(__xludf.DUMMYFUNCTION("""COMPUTED_VALUE"""),0.1002) | G79: =IFERROR(AVERAGEIF($B$46:$B$158, B79, $D$46:$D$158), "") | H79: =IFERROR(AVERAGEIF($B$46:$B$158, B79, $E$46:$E$158), "") | I79: =IFERROR(AVERAGEIF($B$46:$B$158, B79, $F$46:$F$158), "")
B80: =IFERROR(__xludf.DUMMYFUNCTION("""COMPUTED_VALUE"""),"Australian Super") | C80: =IFERROR(__xludf.DUMMYFUNCTION("""COMPUTED_VALUE"""),"Aus & Int shares") | D80: =IFERROR(__xludf.DUMMYFUNCTION("""COMPUTED_VALUE"""),0.1605) | E80: =IFERROR(__xludf.DUMMYFUNCTION("""COMPUTED_VALUE"""),0.10874) | F80: =IFERROR(__xludf.DUMMYFUNCTION("""COMPUTED_VALUE"""),0.09475999999999998) | G80: =IFERROR(AVERAGEIF($B$46:$B$158, B80, $D$46:$D$158), "") | H80: =IFERROR(AVERAGEIF($B$46:$B$158, B80, $E$46:$E$158), "") | I80: =IFERROR(AVERAGEIF($B$46:$B$158, B80, $F$46:$F$158), "")
B81: =IFERROR(__xludf.DUMMYFUNCTION("""COMPUTED_VALUE"""),"Australian Super") | C81: =IFERROR(__xludf.DUMMYFUNCTION("""COMPUTED_VALUE"""),"High Growth") | D81: =IFERROR(__xludf.DUMMYFUNCTION("""COMPUTED_VALUE"""),0.1048) | E81: =IFERROR(__xludf.DUMMYFUNCTION("""COMPUTED_VALUE"""),0.0969) | F81: =IFERROR(__xludf.DUMMYFUNCTION("""COMPUTED_VALUE"""),0.0761) | G81: =IFERROR(AVERAGEIF($B$46:$B$158, B81, $D$46:$D$158), "") | H81: =IFERROR(AVERAGEIF($B$46:$B$158, B81, $E$46:$E$158), "") | I81: =IFERROR(AVERAGEIF($B$46:$B$158, B81, $F$46:$F$158), "")
B82: =IFERROR(__xludf.DUMMYFUNCTION("""COMPUTED_VALUE"""),"UniSuper") | C82: =IFERROR(__xludf.DUMMYFUNCTION("""COMPUTED_VALUE"""),"Aus shares") | D82: =IFERROR(__xludf.DUMMYFUNCTION("""COMPUTED_VALUE"""),0.1338) | E82: =IFERROR(__xludf.DUMMYFUNCTION("""COMPUTED_VALUE"""),0.1257) | F82: =IFERROR(__xludf.DUMMYFUNCTION("""COMPUTED_VALUE"""),0.0889) | G82: =IFERROR(AVERAGEIF($B$46:$B$158, B82, $D$46:$D$158), "") | H82: =IFERROR(AVERAGEIF($B$46:$B$158, B82, $E$46:$E$158), "") | I82: =IFERROR(AVERAGEIF($B$46:$B$158, B82, $F$46:$F$158), "")
B83: =IFERROR(__xludf.DUMMYFUNCTION("""COMPUTED_VALUE"""),"UniSuper") | C83: =IFERROR(__xludf.DUMMYFUNCTION("""COMPUTED_VALUE"""),"Int shares") | D83: =IFERROR(__xludf.DUMMYFUNCTION("""COMPUTED_VALUE"""),0.1642) | E83: =IFERROR(__xludf.DUMMYFUNCTION("""COMPUTED_VALUE"""),0.0861) | F83: =IFERROR(__xludf.DUMMYFUNCTION("""COMPUTED_VALUE"""),0.086) | G83: =IFERROR(AVERAGEIF($B$46:$B$158, B83, $D$46:$D$158), "") | H83: =IFERROR(AVERAGEIF($B$46:$B$158, B83, $E$46:$E$158), "") | I83: =IFERROR(AVERAGEIF($B$46:$B$158, B83, $F$46:$F$158), "")
B84: =IFERROR(__xludf.DUMMYFUNCTION("""COMPUTED_VALUE"""),"UniSuper") | C84: =IFERROR(__xludf.DUMMYFUNCTION("""COMPUTED_VALUE"""),"Aus & Int shares") | D84: =IFERROR(__xludf.DUMMYFUNCTION("""COMPUTED_VALUE"""),0.15204) | E84: =IFERROR(__xludf.DUMMYFUNCTION("""COMPUTED_VALUE"""),0.10194) | F84: =IFERROR(__xludf.DUMMYFUNCTION("""COMPUTED_VALUE"""),0.08715999999999999) | G84: =IFERROR(AVERAGEIF($B$46:$B$158, B84, $D$46:$D$158), "") | H84: =IFERROR(AVERAGEIF($B$46:$B$158, B84, $E$46:$E$158), "") | I84: =IFERROR(AVERAGEIF($B$46:$B$158, B84, $F$46:$F$158), "")
B85: =IFERROR(__xludf.DUMMYFUNCTION("""COMPUTED_VALUE"""),"UniSuper") | C85: =IFERROR(__xludf.DUMMYFUNCTION("""COMPUTED_VALUE"""),"High Growth") | D85: =IFERROR(__xludf.DUMMYFUNCTION("""COMPUTED_VALUE"""),0.1398) | E85: =IFERROR(__xludf.DUMMYFUNCTION("""COMPUTED_VALUE"""),0.1014) | F85: =IFERROR(__xludf.DUMMYFUNCTION("""COMPUTED_VALUE"""),0.0814) | G85: =IFERROR(AVERAGEIF($B$46:$B$158, B85, $D$46:$D$158), "") | H85: =IFERROR(AVERAGEIF($B$46:$B$158, B85, $E$46:$E$158), "") | I85: =IFERROR(AVERAGEIF($B$46:$B$158, B85, $F$46:$F$158), "")
B86: =IFERROR(__xludf.DUMMYFUNCTION("""COMPUTED_VALUE"""),"UniSuper") | C86: =IFERROR(__xludf.DUMMYFUNCTION("""COMPUTED_VALUE"""),"SRI") | D86: =IFERROR(__xludf.DUMMYFUNCTION("""COMPUTED_VALUE"""),0.1381) | E86: =IFERROR(__xludf.DUMMYFUNCTION("""COMPUTED_VALUE"""),0.0816) | F86: =IFERROR(__xludf.DUMMYFUNCTION("""COMPUTED_VALUE"""),0.0848) | G86: =IFERROR(AVERAGEIF($B$46:$B$158, B86, $D$46:$D$158), "") | H86: =IFERROR(AVERAGEIF($B$46:$B$158, B86, $E$46:$E$158), "") | I86: =IFERROR(AVERAGEIF($B$46:$B$158, B86, $F$46:$F$158), "")
B87: =IFERROR(__xludf.DUMMYFUNCTION("""COMPUTED_VALUE"""),"HESTA") | C87: =IFERROR(__xludf.DUMMYFUNCTION("""COMPUTED_VALUE"""),"Aus shares") | D87: =IFERROR(__xludf.DUMMYFUNCTION("""COMPUTED_VALUE"""),0.147) | E87: =IFERROR(__xludf.DUMMYFUNCTION("""COMPUTED_VALUE"""),0.1193) | F87: =IFERROR(__xludf.DUMMYFUNCTION("""COMPUTED_VALUE"""),0.0755) | G87: =IFERROR(AVERAGEIF($B$46:$B$158, B87, $D$46:$D$158), "") | H87: =IFERROR(AVERAGEIF($B$46:$B$158, B87, $E$46:$E$158), "") | I87: =IFERROR(AVERAGEIF($B$46:$B$158, B87, $F$46:$F$158), "")
B88: =IFERROR(__xludf.DUMMYFUNCTION("""COMPUTED_VALUE"""),"HESTA") | C88: =IFERROR(__xludf.DUMMYFUNCTION("""COMPUTED_VALUE"""),"Int shares") | D88: =IFERROR(__xludf.DUMMYFUNCTION("""COMPUTED_VALUE"""),0.1796) | E88: =IFERROR(__xludf.DUMMYFUNCTION("""COMPUTED_VALUE"""),0.1065) | F88: =IFERROR(__xludf.DUMMYFUNCTION("""COMPUTED_VALUE"""),0.0813) | G88: =IFERROR(AVERAGEIF($B$46:$B$158, B88, $D$46:$D$158), "") | H88: =IFERROR(AVERAGEIF($B$46:$B$158, B88, $E$46:$E$158), "") | I88: =IFERROR(AVERAGEIF($B$46:$B$158, B88, $F$46:$F$158), "")
B89: =IFERROR(__xludf.DUMMYFUNCTION("""COMPUTED_VALUE"""),"HESTA") | C89: =IFERROR(__xludf.DUMMYFUNCTION("""COMPUTED_VALUE"""),"Aus & Int shares") | D89: =IFERROR(__xludf.DUMMYFUNCTION("""COMPUTED_VALUE"""),0.16656) | E89: =IFERROR(__xludf.DUMMYFUNCTION("""COMPUTED_VALUE"""),0.11162) | F89: =IFERROR(__xludf.DUMMYFUNCTION("""COMPUTED_VALUE"""),0.07898) | G89: =IFERROR(AVERAGEIF($B$46:$B$158, B89, $D$46:$D$158), "") | H89: =IFERROR(AVERAGEIF($B$46:$B$158, B89, $E$46:$E$158), "") | I89: =IFERROR(AVERAGEIF($B$46:$B$158, B89, $F$46:$F$158), "")
B90: =IFERROR(__xludf.DUMMYFUNCTION("""COMPUTED_VALUE"""),"HESTA") | C90: =IFERROR(__xludf.DUMMYFUNCTION("""COMPUTED_VALUE"""),"High Growth") | D90: =IFERROR(__xludf.DUMMYFUNCTION("""COMPUTED_VALUE"""),0.1258) | E90: =IFERROR(__xludf.DUMMYFUNCTION("""COMPUTED_VALUE"""),0.1127) | F90: =IFERROR(__xludf.DUMMYFUNCTION("""COMPUTED_VALUE"""),0.083) | G90: =IFERROR(AVERAGEIF($B$46:$B$158, B90, $D$46:$D$158), "") | H90: =IFERROR(AVERAGEIF($B$46:$B$158, B90, $E$46:$E$158), "") | I90: =IFERROR(AVERAGEIF($B$46:$B$158, B90, $F$46:$F$158), "")
B91: =IFERROR(__xludf.DUMMYFUNCTION("""COMPUTED_VALUE"""),"CareSuper") | C91: =IFERROR(__xludf.DUMMYFUNCTION("""COMPUTED_VALUE"""),"Aus shares") | D91: =IFERROR(__xludf.DUMMYFUNCTION("""COMPUTED_VALUE"""),0.15) | F91: =IFERROR(__xludf.DUMMYFUNCTION("""COMPUTED_VALUE"""),0.0748) | G91: =IFERROR(AVERAGEIF($B$46:$B$158, B91, $D$46:$D$158), "") | H91: =IFERROR(AVERAGEIF($B$46:$B$158, B91, $E$46:$E$158), "") | I91: =IFERROR(AVERAGEIF($B$46:$B$158, B91, $F$46:$F$158), "")
B92: =IFERROR(__xludf.DUMMYFUNCTION("""COMPUTED_VALUE"""),"CareSuper") | C92: =IFERROR(__xludf.DUMMYFUNCTION("""COMPUTED_VALUE"""),"Int shares") | D92: =IFERROR(__xludf.DUMMYFUNCTION("""COMPUTED_VALUE"""),0.1779) | F92: =IFERROR(__xludf.DUMMYFUNCTION("""COMPUTED_VALUE"""),0.0795) | G92: =IFERROR(AVERAGEIF($B$46:$B$158, B92, $D$46:$D$158), "") | H92: =IFERROR(AVERAGEIF($B$46:$B$158, B92, $E$46:$E$158), "") | I92: =IFERROR(AVERAGEIF($B$46:$B$158, B92, $F$46:$F$158), "")
B93: =IFERROR(__xludf.DUMMYFUNCTION("""COMPUTED_VALUE"""),"CareSuper") | C93: =IFERROR(__xludf.DUMMYFUNCTION("""COMPUTED_VALUE"""),"Aus & Int shares") | D93: =IFERROR(__xludf.DUMMYFUNCTION("""COMPUTED_VALUE"""),0.16674) | F93: =IFERROR(__xludf.DUMMYFUNCTION("""COMPUTED_VALUE"""),0.07762) | G93: =IFERROR(AVERAGEIF($B$46:$B$158, B93, $D$46:$D$158), "") | H93: =IFERROR(AVERAGEIF($B$46:$B$158, B93, $E$46:$E$158), "") | I93: =IFERROR(AVERAGEIF($B$46:$B$158, B93, $F$46:$F$158), "")
B94: =IFERROR(__xludf.DUMMYFUNCTION("""COMPUTED_VALUE"""),"CareSuper") | C94: =IFERROR(__xludf.DUMMYFUNCTION("""COMPUTED_VALUE"""),"High Growth") | D94: =IFERROR(__xludf.DUMMYFUNCTION("""COMPUTED_VALUE"""),0.117) | F94: =IFERROR(__xludf.DUMMYFUNCTION("""COMPUTED_VALUE"""),0.0695) | G94: =IFERROR(AVERAGEIF($B$46:$B$158, B94, $D$46:$D$158), "") | H94: =IFERROR(AVERAGEIF($B$46:$B$158, B94, $E$46:$E$158), "") | I94: =IFERROR(AVERAGEIF($B$46:$B$158, B94, $F$46:$F$158), "")
B95: =IFERROR(__xludf.DUMMYFUNCTION("""COMPUTED_VALUE"""),"Cbus") | C95: =IFERROR(__xludf.DUMMYFUNCTION("""COMPUTED_VALUE"""),"Aus shares") | D95: =IFERROR(__xludf.DUMMYFUNCTION("""COMPUTED_VALUE"""),0.1486) | G95: =IFERROR(AVERAGEIF($B$46:$B$158, B95, $D$46:$D$158), "") | H95: =IFERROR(AVERAGEIF($B$46:$B$158, B95, $E$46:$E$158), "") | I95: =IFERROR(AVERAGEIF($B$46:$B$158, B95, $F$46:$F$158), "")
B96: =IFERROR(__xludf.DUMMYFUNCTION("""COMPUTED_VALUE"""),"Cbus") | C96: =IFERROR(__xludf.DUMMYFUNCTION("""COMPUTED_VALUE"""),"Int shares") | D96: =IFERROR(__xludf.DUMMYFUNCTION("""COMPUTED_VALUE"""),0.1871) | G96: =IFERROR(AVERAGEIF($B$46:$B$158, B96, $D$46:$D$158), "") | H96: =IFERROR(AVERAGEIF($B$46:$B$158, B96, $E$46:$E$158), "") | I96: =IFERROR(AVERAGEIF($B$46:$B$158, B96, $F$46:$F$158), "")
B97: =IFERROR(__xludf.DUMMYFUNCTION("""COMPUTED_VALUE"""),"Cbus") | C97: =IFERROR(__xludf.DUMMYFUNCTION("""COMPUTED_VALUE"""),"Aus & Int shares") | D97: =IFERROR(__xludf.DUMMYFUNCTION("""COMPUTED_VALUE"""),0.1717) | G97: =IFERROR(AVERAGEIF($B$46:$B$158, B97, $D$46:$D$158), "") | H97: =IFERROR(AVERAGEIF($B$46:$B$158, B97, $E$46:$E$158), "") | I97: =IFERROR(AVERAGEIF($B$46:$B$158, B97, $F$46:$F$158), "")
B98: =IFERROR(__xludf.DUMMYFUNCTION("""COMPUTED_VALUE"""),"Cbus") | C98: =IFERROR(__xludf.DUMMYFUNCTION("""COMPUTED_VALUE"""),"High Growth") | D98: =IFERROR(__xludf.DUMMYFUNCTION("""COMPUTED_VALUE"""),0.1257) | F98: =IFERROR(__xludf.DUMMYFUNCTION("""COMPUTED_VALUE"""),0.0755) | G98: =IFERROR(AVERAGEIF($B$46:$B$158, B98, $D$46:$D$158), "") | H98: =IFERROR(AVERAGEIF($B$46:$B$158, B98, $E$46:$E$158), "") | I98: =IFERROR(AVERAGEIF($B$46:$B$158, B98, $F$46:$F$158), "")
B99: =IFERROR(__xludf.DUMMYFUNCTION("""COMPUTED_VALUE"""),"Spirit") | C99: =IFERROR(__xludf.DUMMYFUNCTION("""COMPUTED_VALUE"""),"Aus shares") | D99: =IFERROR(__xludf.DUMMYFUNCTION("""COMPUTED_VALUE"""),0.1354) | E99: =IFERROR(__xludf.DUMMYFUNCTION("""COMPUTED_VALUE"""),0.1048) | F99: =IFERROR(__xludf.DUMMYFUNCTION("""COMPUTED_VALUE"""),0.0678) | G99: =IFERROR(AVERAGEIF($B$46:$B$158, B99, $D$46:$D$158), "") | H99: =IFERROR(AVERAGEIF($B$46:$B$158, B99, $E$46:$E$158), "") | I99: =IFERROR(AVERAGEIF($B$46:$B$158, B99, $F$46:$F$158), "")
B100: =IFERROR(__xludf.DUMMYFUNCTION("""COMPUTED_VALUE"""),"Spirit") | C100: =IFERROR(__xludf.DUMMYFUNCTION("""COMPUTED_VALUE"""),"Int shares") | D100: =IFERROR(__xludf.DUMMYFUNCTION("""COMPUTED_VALUE"""),0.1666) | E100: =IFERROR(__xludf.DUMMYFUNCTION("""COMPUTED_VALUE"""),0.108) | F100: =IFERROR(__xludf.DUMMYFUNCTION("""COMPUTED_VALUE"""),0.0747) | G100: =IFERROR(AVERAGEIF($B$46:$B$158, B100, $D$46:$D$158), "") | H100: =IFERROR(AVERAGEIF($B$46:$B$158, B100, $E$46:$E$158), "") | I100: =IFERROR(AVERAGEIF($B$46:$B$158, B100, $F$46:$F$158), "")
B101: =IFERROR(__xludf.DUMMYFUNCTION("""COMPUTED_VALUE"""),"Spirit") | C101: =IFERROR(__xludf.DUMMYFUNCTION("""COMPUTED_VALUE"""),"Aus & Int shares") | D101: =IFERROR(__xludf.DUMMYFUNCTION("""COMPUTED_VALUE"""),0.15411999999999998) | E101: =IFERROR(__xludf.DUMMYFUNCTION("""COMPUTED_VALUE"""),0.10672000000000001) | F101: =IFERROR(__xludf.DUMMYFUNCTION("""COMPUTED_VALUE"""),0.07194) | G101: =IFERROR(AVERAGEIF($B$46:$B$158, B101, $D$46:$D$158), "") | H101: =IFERROR(AVERAGEIF($B$46:$B$158, B101, $E$46:$E$158), "") | I101: =IFERROR(AVERAGEIF($B$46:$B$158, B101, $F$46:$F$158), "")
B102: =IFERROR(__xludf.DUMMYFUNCTION("""COMPUTED_VALUE"""),"Spirit") | C102: =IFERROR(__xludf.DUMMYFUNCTION("""COMPUTED_VALUE"""),"High Growth") | D102: =IFERROR(__xludf.DUMMYFUNCTION("""COMPUTED_VALUE"""),0.1201) | E102: =IFERROR(__xludf.DUMMYFUNCTION("""COMPUTED_VALUE"""),0.0945) | F102: =IFERROR(__xludf.DUMMYFUNCTION("""COMPUTED_VALUE"""),0.0704) | G102: =IFERROR(AVERAGEIF($B$46:$B$158, B102, $D$46:$D$158), "") | H102: =IFERROR(AVERAGEIF($B$46:$B$158, B102, $E$46:$E$158), "") | I102: =IFERROR(AVERAGEIF($B$46:$B$158, B102, $F$46:$F$158), "")
B103: =IFERROR(__xludf.DUMMYFUNCTION("""COMPUTED_VALUE"""),"Catholic Super") | C103: =IFERROR(__xludf.DUMMYFUNCTION("""COMPUTED_VALUE"""),"Aus shares") | D103: =IFERROR(__xludf.DUMMYFUNCTION("""COMPUTED_VALUE"""),0.1424) | E103: =IFERROR(__xludf.DUMMYFUNCTION("""COMPUTED_VALUE"""),0.1111) | F103: =IFERROR(__xludf.DUMMYFUNCTION("""COMPUTED_VALUE"""),0.0676) | G103: =IFERROR(AVERAGEIF($B$46:$B$158, B103, $D$46:$D$158), "") | H103: =IFERROR(AVERAGEIF($B$46:$B$158, B103, $E$46:$E$158), "") | I103: =IFERROR(AVERAGEIF($B$46:$B$158, B103, $F$46:$F$158), "")
...

Sheet Logic Sheet
B2: Super Index Reference
B3: =MATCH('Advanced Savings'!F9,'Super Data'!B6:B39,0)
B4: Fixed p.a | C4: % of AUM | D4: Admin fee cap | E4: Investment fees
B5: {=INDEX('Super Data'!D6:H39,B3,0)} | C5: 0.0015 | D5: 750 | E5: 0.0078 | F5: Nil
B7: =MATCH('Advanced Savings'!F9,'Super Data'!B46:B158,0) | C7: Performance
B8: Name | C8: 1 year | D8: 3 years | E8: 5 years
B9: ='Advanced Savings'!F9 | C9: {=INDEX('Super Data'!G46:I158,(B7),0)} | D9: 0.11161 | E9: 0.088745
B11: Tax Bracket
B12: =IF(Income!D5 <= 18200, 0, IF(Income!D5 <= 45000, 0.16, IF(Income!D5 <= 135000, 0.3, IF(Income!D5 <= 190000, 0.37, 0.45))))
B19: Super Index Reference
B20: =MATCH('Advanced Savings'!F26,'Super Data'!B6:B39,0)
B21: Fixed p.a | C21: % of AUM | D21: Admin fee cap | E21: Investment fees
B22: {=INDEX('Super Data'!D6:H39,B20,0)} | C22: 0.001 | D22: 300 | E22: 0.0075 | F22: 0.07% / 0%
B24: =MATCH('Advanced Savings'!F26,'Super Data'!B46:B158,0) | C24: Performance
B25: Name | C25: 1 year | D25: 3 years | E25: 5 years
B26: ='Advanced Savings'!F26 | C26: {=INDEX('Super Data'!G46:I158,(B24),0)} | D26: 0.11439429 | E26: 0.074335
B28: Tax Bracket
B29: =IF(Income!D23 <= 18200, 0, IF(Income!D23 <= 45000, 0.16, IF(Income!D23 <= 135000, 0.3, IF(Income!D23 <= 190000, 0.37, 0.45))))
